Workbook

Sheet Аэрофлот
A1: Отчет о финансовом положении | I1: Отчет о прибылях и убытках
A2: на 31 декабря 202X года в миллионах рублей | I2: за 202X год в миллионах рублей, если не указано иное
B3: 2020 г. | C3: 2021 г. | D3: 2023 г. | E3: 2024 г. | J3: 2020 г. | K3: 2021 г. | L3: 2023 г. | M3: 2024 г.
A4: АКТИВЫ | I4: Выручка от перевозок | J4: 270476 | K4: 457219 | L4: 596579 | M4: 838980
A5: Оборотные активы | I5: Прочая выручка | J5: 31706 | K5: 34514 | L5: 15615 | M5: 17805
A6: Денежные средства и их эквиваленты | B6: 88944 | C6: 74180 | D6: 83117 | E6: 67814 | I6: Выручка | J6: 302182 | K6: 491733 | L6: 612194 | M6: 856785
A7: Краткосрочные финансовые инвестиции | B7: 4831 | C7: 19573 | D7: 34009 | E7: 37622
A8: Дебиторская задолженность и предоплаты | B8: 67051 | C8: 73213 | D8: 82262 | E8: 87450 | I8: Операционные расходы, за исключением расходов на оплату труда и амортизации | J8: -222070 | K8: -326216 | L8: -411345 | M8: -582213
A9: Предоплата по текущему налогу на прибыль | B9: 469 | C9: 153 | D9: 3521 | E9: 1484 | I9: Расходы на оплату труда | J9: -65445 | K9: -68439 | L9: -77447 | M9: -99848
A10: Страховые депозиты по аренде воздушных судов | B10: 2739 | C10: 3103 | D10: 1827 | E10: 1485 | I10: Амортизация | J10: -118633 | K10: -120506 | L10: -135958 | M10: -113972
A11: Расходные запчасти и запасы | B11: 16889 | C11: 17911 | D11: 31895 | E11: 57728 | I11: Прочие операционные доходы/(расходы), нетто | J11: 11813 | K11: 18413 | L11: 194809 | M11: 38785
A12: Краткосрочные финансовые активы по договорам аренды | B12: 4159 | C12: 2211 | D12: 14171 | E12: 154 | I12: Операционные расходы | J12: -394335 | K12: -496748 | L12: -429941 | M12: -757248
A13: Итого оборотные активы | B13: 185082 | C13: 190344 | D13: 250802 | E13: 253737
I14: Прибыль / убыток от операционной деятельности | J14: -92153 | K14: -5015 | L14: 182253 | M14: 99537
A15: Внеоборотные активы | I15: Прибыль / убыток от обесценения и изменения справедливой стоимости инвестиций, нетто | J15: -557 | K15: -265 | L15: 471 | M15: 614
A16: Активы в форме права пользования | B16: 635406 | C16: 725421 | D16: 619883 | E16: 557557 | I16: Финансовые доходы | J16: 4938 | K16: 12331 | L16: 15968 | M16: 22464
A17: Основные средства | B17: 19825 | C17: 19893 | D17: 104922 | E17: 159838 | I17: Финансовые расходы | J17: -47252 | K17: -41407 | L17: -210060 | M17: -79796
A18: Предоплата за воздушные суда | B18: 27275 | C18: 12743 | I18: Реализация результата хеджирования | J18: -13254 | K18: -8291 | L18: - | M18: -2002
A19: Отложенные налоговые активы | B19: 75430 | C19: 85531 | D19: 93080 | E19: 130228 | I19: Доля в финансовых результатах ассоциированных компаний | J19: -143 | K19: 153 | L19: 18 | M19: 2437
A20: Долгосрочные финансовые инвестиции | B20: 5464 | C20: 5360 | D20: 5335 | E20: 6123 | I20: Результат от выбытия дочерних компаний | J20: -5066 | K20: - | L20: - | M20: -1045
A21: Нематериальные активы | B21: 2414 | C21: 3221 | D21: 7475 | E21: 21245 | I21: Убыток до налогообложения | J21: -153487 | K21: -42494 | L21: -11350 | M21: 42209
A22: Долгосрочные финансовые активы по договорам аренды | B22: 18606 | C22: 25467 | D22: 9800 | I22: Налог на прибыль | J22: 30279 | K22: 8034 | L22: -2671 | M22: 12811
A23: Страховые депозиты по аренде воздушных судов | B23: 1867 | C23: 1934 | D23: 139 | E23: 139
A24: Инвестиции в ассоциированные компании | B24: 419 | C24: 538 | D24: 518 | E24: 1541 | I24: УБЫТОК / ПРИБЫЛЬ ЗА ГОД | J24: -123208 | K24: -34460 | L24: -14021 | M24: 55020
A25: Прочие внеоборотные активы | B25: 44416 | C25: 38998 | D25: 22060 | E25: 26488 | I25: Приходящийся на:
A26: Итого внеоборотные активы | B26: 831122 | C26: 919106 | D26: 863212 | E26: 903159 | I26: Акционеров Компании | J26: -117613 | K26: -34106 | L26: -8862 | M26: 58501
I27: Держателей неконтролирующих долей участия | J27: -5595 | K27: -354 | L27: -5159 | M27: -3481
A28: ИТОГО АКТИВЫ | B28: 1016204 | C28: 1109450 | D28: 1114014 | E28: 1156896
I30: ИСТОЧНИКИ
A31: ОБЯЗАТЕЛЬСТВА И КАПИТАЛ | I31: Отчет о прибылях и убытках и отчет о финансовом положении - | J31: https://ir.aeroflot.ru/reporting/financial-results/ifrs/
A33: Краткосрочные обязательства
A34: Кредиторская задолженность и начисленные обязательства | B34: 52186 | C34: 63211 | D34: 98913 | E34: 116717
A35: Незаработанная транспортная выручка | B35: 44622 | C35: 54837 | D35: 45571 | E35: 64774
A36: Отложенная выручка по программе премирования пассажиров | B36: 1929 | C36: 2043 | D36: 2775 | E36: 15767
A37: Резервы под обязательства | B37: 20859 | C37: 27252 | D37: 42386 | E37: 50711
A38: Обязательства по аренде | B38: 126761 | C38: 107604 | D38: 104876 | E38: 140596
A39: Краткосрочные кредиты и займы и краткосрочная часть долгосрочных кредитов и займов | B39: 34924 | C39: 17500 | D39: 44178 | E39: 19746
A40: Обязательства по текущему налогу на прибыль | B40: 4 | C40: 141 | D40: 905 | E40: 754
A41: Итого краткосрочные обязательства | B41: 281285 | C41: 272588 | D41: 339604 | E41: 409065
A43: Долгосрочные обязательства
A44: Долгосрочные кредиты и займы | B44: 53711 | C44: 114768 | D44: 60190 | E44: 40722
A45: Обязательства по аренде | B45: 535746 | C45: 557679 | D45: 538007 | E45: 501945
A46: Резервы под обязательства | B46: 232868 | C46: 287355 | D46: 255304 | E46: 272475
A47: Отложенные налоговые обязательства | B47: 77 | C47: 85 | D47: 77 | E47: 204
A48: Отложенная выручка по программе премирования пассажиров | B48: 7197 | C48: 7861 | D48: 9673
A49: Прочие долгосрочные обязательства | B49: 20666 | C49: 15552 | D49: 9913 | E49: 4982
A50: Итого долгосрочные обязательства | B50: 850265 | C50: 983300 | D50: 873164 | E50: 820328
A52: ИТОГО ОБЯЗАТЕЛЬСТВА | B52: 1131550 | C52: 1255888 | D52: 1212768 | E52: 1229393
A55: Капитал
A56: Уставный капитал | B56: 2693 | C56: 2693 | D56: 4224 | E56: 4224
A57: Добавочный капитал | B57: 78701 | C57: 78701 | D57: 144402 | E57: 143482
A58: Резерв выкупленных собственных акций | B58: -7040 | C58: -7040 | D58: -7040 | E58: -7040
A59: Накопленная прибыль от продажи собственных акций | B59: 7864 | C59: 7864 | D59: 7864 | E59: 7864
A60: Резерв по инструментам хеджирования | B60: -48330 | C60: -44949
A61: Накопленный убыток | B61: -141664 | C61: -175770 | D61: -234993 | E61: -176492
A62: Капитал, приходящийся на акционеров Компании | B62: -107776 | C62: -138501 | D62: -85543 | E62: -55712
A63: Держатели неконтролирующих долей участия | B63: -7570 | C63: -7937 | D63: -13211 | E63: -16785
A65: ИТОГО КАПИТАЛ | B65: -115346 | C65: -146438 | D65: -98754 | E65: -72497
A67: ИТОГО ОБЯЗАТЕЛЬСТВА И КАПИТАЛ | B67: 1016204 | C67: 1109450 | D67: 1114014 | E67: 1156896
A70: Метрики
A72: Ликвидность
A73: Текущая | B73: ='Аэрофлот'!B13/'Аэрофлот'!B41 -> 0.65798745 | C73: ='Аэрофлот'!C13/'Аэрофлот'!C41 -> 0.69828459 | D73: ='Аэрофлот'!D13/'Аэрофлот'!D41 -> 0.73851309 | E73: ='Аэрофлот'!E13/'Аэрофлот'!E41 -> 0.62028528
A74: Быстрая | B74: =('Аэрофлот'!B6+'Аэрофлот'!B7+'Аэрофлот'!B8)/'Аэрофлот'!B41 -> 0.57175463 | C74: =('Аэрофлот'!C6+'Аэрофлот'!C7+'Аэрофлот'!C8)/'Аэрофлот'!C41 -> 0.61252146 | D74: =('Аэрофлот'!D6+'Аэрофлот'!D7+'Аэрофлот'!D8)/'Аэрофлот'!D41 -> 0.58711912 | E74: =('Аэрофлот'!E6+'Аэрофлот'!E7+'Аэрофлот'!E8)/'Аэрофлот'!E41 -> 0.47152897
A75: Абсолютная | B75: =('Аэрофлот'!B6+'Аэрофлот'!B7)/'Аэрофлот'!B41 -> 0.33338073 | C75: =('Аэрофлот'!C6+'Аэрофлот'!C7)/'Аэрофлот'!C41 -> 0.34393664 | D75: =('Аэрофлот'!D6+'Аэрофлот'!D7)/'Аэрофлот'!D41 -> 0.34488993 | E75: =('Аэрофлот'!E6+'Аэрофлот'!E7)/'Аэрофлот'!E41 -> 0.25774877
A77: Финансовая устойчивость
A78: Коэффициент автономии | B78: =abs('Аэрофлот'!B65)/(abs('Аэрофлот'!B65)+'Аэрофлот'!B52) -> 0.092506512 | C78: =abs('Аэрофлот'!C65)/(abs('Аэрофлот'!C65)+'Аэрофлот'!C52) -> 0.10442508 | D78: =abs('Аэрофлот'!D65)/(abs('Аэрофлот'!D65)+'Аэрофлот'!D52) -> 0.07529725 | E78: =abs('Аэрофлот'!E65)/(abs('Аэрофлот'!E65)+'Аэрофлот'!E52) -> 0.055685964
A79: Коэффициент соотношения заемных и собственных средств | B79: =('Аэрофлот'!B41+'Аэрофлот'!B50)/'Аэрофлот'!B65 -> -9.8100498 | C79: =('Аэрофлот'!C41+'Аэрофлот'!C50)/'Аэрофлот'!C65 -> -8.5762439 | D79: =('Аэрофлот'!D41+'Аэрофлот'!D50)/'Аэрофлот'!D65 -> -12.280697 | E79: =('Аэрофлот'!E41+'Аэрофлот'!E50)/'Аэрофлот'!E65 -> -16.957847
A80: Коэффициент финансового левериджа | B80: ='Аэрофлот'!B28/'Аэрофлот'!B65 -> -8.8100498 | C80: ='Аэрофлот'!C28/'Аэрофлот'!C65 -> -7.5762439 | D80: ='Аэрофлот'!D28/'Аэрофлот'!D65 -> -11.280697 | E80: ='Аэрофлот'!E28/'Аэрофлот'!E65 -> -15.957847
A82: Коэффициенты деловой активности
A83: Оборачиваемость активов | B83: =('Аэрофлот'!J6)/(('Аэрофлот'!B119+'Аэрофлот'!B28)/2) -> 0.31000625 | C83: =('Аэрофлот'!K6)/(('Аэрофлот'!B28+'Аэрофлот'!C28)/2) -> 0.46266514 | D83: =('Аэрофлот'!L6)/(('Аэрофлот'!C28+'Аэрофлот'!D28)/2) -> 0.55066689 | E83: =('Аэрофлот'!M6)/(('Аэрофлот'!D28+'Аэрофлот'!E28)/2) -> 0.75457416
A84: Оборачиваемость дебиторской задолженности | B84: =(('Аэрофлот'!B120+'Аэрофлот'!B8)/2)/('Аэрофлот'!J6) -> 0.27056211 | C84: =(('Аэрофлот'!B8+'Аэрофлот'!C8)/2)/('Аэрофлот'!K6) -> 0.14262211 | D84: =(('Аэрофлот'!C8+'Аэрофлот'!D8)/2)/('Аэрофлот'!L6) -> 0.12698181 | E84: =(('Аэрофлот'!D8+'Аэрофлот'!E8)/2)/('Аэрофлот'!M6) -> 0.099040016
A86: Коэффициенты рентабельности
A87: Рентабельность продаж (ROS) | B87: ='Аэрофлот'!J24*100/'Аэрофлот'!J6 -> -40.772779 | C87: ='Аэрофлот'!K24*100/'Аэрофлот'!K6 -> -7.0078681 | D87: ='Аэрофлот'!L24*100/'Аэрофлот'!L6 -> -2.2902871 | E87: ='Аэрофлот'!M24*100/'Аэрофлот'!M6 -> 6.4216811
A88: Рентабельность активов (ROA) | B88: - | C88: ='Аэрофлот'!K24*100/(('Аэрофлот'!B28+'Аэрофлот'!C28)/2) -> -3.2422963 | D88: ='Аэрофлот'!L24*100/(('Аэрофлот'!C28+'Аэрофлот'!D28)/2) -> -1.2611853 | E88: ='Аэрофлот'!M24*100/(('Аэрофлот'!D28+'Аэрофлот'!E28)/2) -> 4.8456346
A89: Рентабельность собственного капитала (ROE) | B89: - | C89: =('Аэрофлот'!K24)*100/(('Аэрофлот'!B65+'Аэрофлот'!C65)/2) -> 26.327048 | D89: =('Аэрофлот'!L24)*100/(('Аэрофлот'!C65+'Аэрофлот'!D65)/2) -> 11.436752 | E89: =('Аэрофлот'!M24)*100/(('Аэрофлот'!D65+'Аэрофлот'!E65)/2) -> -64.256559
A118: Метрики за 2019 год
A119: Итоговые активы | B119: 933318
A120: Дебиторская задолженность и предоплаты | B120: 96467
A121: Кредиторская задоленность | B121: 71737
A122: Итого капитал | B122: 1950

Sheet TurkishAirlines
A1: Отчет о финансовом положении | H1: Отчет о прибылях и убытках
A2: на 31 декабря 202X года в миллионах рублей | H2: за 202X год в миллионах рублей, если не указано иное
B3: 2020 г. | C3: 2021 г. | D3: 2023 г. | E3: 2024 г. | I3: 2020 г. | J3: 2021 г. | K3: 2023 г. | L3: 2024 г.
A4: АКТИВЫ | H4: ПРИБЫЛЬ ИЛИ УБЫТОК
A6: ВНЕОБОРОТНЫЕ АКТИВЫ | H6: Выручка | I6: 498316 | J6: 790764 | K6: 1905722 | L6: 2312238
A7: Финансовые вложения | B7: 5550 | C7: 6512 | D7: 36218 | E7: 113526 | H7: Себестоимость продаж | I7: -471972 | J7: -615828 | K7: -1461460 | L7: -1871394
A8: Прочая дебиторская задолженность | H8: ВАЛОВАЯ ПРИБЫЛЬ | I8: 26344 | J8: 174936 | K8: 444262 | L8: 440844
A9: Аффилированные лица | B9: - | C9: - | D9: - | E9: 1224
A10: Третьи стороны | B10: 88800 | C10: 64084 | D10: 126945 | E10: 127704 | H10: Общие и административные расходы | I10: -16206 | J10: -18796 | K10: -40859 | L10: -57528
A11: Инвестиции, учитываемые методом долевого участия | B11: 18944 | C11: 17538 | D11: 45227 | E11: 65688 | H11: Коммерческие и маркетинговые расходы | I11: -49358 | J11: -61790 | K11: -160160 | L11: -187476
A12: Инвестиционная собственность | B12: - | C12: - | D12: 3913 | E12: 4386 | H12: Прочие операционные доходы | I12: 24420 | J12: 12876 | K12: 46319 | L12: 61812
A13: Основные средства | B13: 306730 | C13: 322936 | D13: 552825 | E13: 719610 | H13: Прочие операционные расходы | I13: -4070 | J13: -2590 | K13: -29393 | L13: -11526
A14: Активы в форме права пользования | B14: 1093498 | C14: 1118140 | D14: 1540448 | E14: 1797750 | H14: ОПЕРАЦИОННАЯ ПРИБЫЛЬ / УБЫТОК ДО УЧЕТА ИНВЕСТИЦИОННОЙ ДЕЯТЕЛЬНОСТИ | I14: -18870 | J14: 104636 | K14: 260169 | L14: 246126
A15: Нематериальные активы
A16: Прочие нематериальные активы | B16: 6586 | C16: 6068 | D16: 7917 | E16: 11424 | H16: Доходы от инвестиционной деятельности | I16: 14060 | J16: 15318 | K16: 84903 | L16: 170136
A17: Гудвил | B17: 888 | C17: 888 | D17: 2457 | E17: 2754 | H17: Расходы от инвестиционной деятельности | I17: -814 | J17: -518 | K17: -5915 | L17: -7650
A18: Расходы будущих периодов | B18: 59052 | C18: 62086 | D18: 117754 | E18: 172992 | H18: Доля в прибыли / убытке инвестиций, учитываемых методом долевого участия | I18: -6438 | J18: 5550 | K18: 21112 | L18: 17952
A19: Отложенный налоговый актив | B19: - | C19: 74 | D19: 30212 | E19: 41004 | H19: ОПЕРАЦИОННАЯ ПРИБЫЛЬ / УБЫТОК | I19: -12062 | J19: 124986 | K19: 360269 | L19: 426564
A20: ИТОГО ВНЕОБОРОТНЫЕ АКТИВЫ | B20: 1580048 | C20: 1598326 | D20: 2463916 | E20: 3058062
H21: Финансовые доходы | I21: 5328 | J21: 7474 | K21: 55601 | L21: 101082
A22: ОБОРОТНЫЕ АКТИВЫ | H22: Финансовые расходы | I22: -61790 | J22: -56758 | K22: -84721 | L22: -155856
A23: Денежные средства и денежные эквиваленты | B23: 134014 | C23: 198098 | D23: 62153 | E23: 277542 | H23: Денежная прибыль | I23: - | J23: - | K23: 182 | L23: 204
A24: Финансовые вложения | B24: 1332 | C24: 370 | D24: 486304 | E24: 341292 | H24: ПРИБЫЛЬ / УБЫТОК ДО НАЛОГООБЛОЖЕНИЯ | I24: -68524 | J24: 75702 | K24: 331331 | L24: 371994
A25: Дебиторская задолженность
A26: Аффилированные лица | B26: 1332 | C26: 1776 | D26: 4550 | E26: 4386 | H26: Налоговые доходы / расходы | I26: 6660 | J26: -4736 | K26: 216580 | L26: -22644
A27: Третьи стороны | B27: 45806 | C27: 66674 | D27: 73346 | E27: 87924 | H27: Текущий налог на прибыль | I27: - | J27: -2072 | K27: -6006 | L27: -39474
A28: Прочая дебиторская задолженность | H28: Отложенный налоговый доход / расход | I28: 6660 | J28: -2664 | K28: 222586 | L28: 16830
A29: Аффилированные лица | B29: 444 | C29: 444 | D29: 819 | E29: 918 | H29: Отложенный налоговый расход | I29: - | J29: -2664 | K29: -54327 | L29: -
A30: Третьи стороны | B30: 81030 | C30: 58534 | D30: 80080 | E30: 138618 | H30: Влияние корректировки на инфляцию на отложенный налоговый доход | I30: - | J30: - | K30: 276913 | L30: -
A31: Производные финансовые инструменты | B31: 148 | C31: 4366 | D31: 1638 | E31: 12138 | H31: ЧИСТАЯ ПРИБЫЛЬ / УБЫТОК ЗА ГОД | I31: -61864 | J31: 70966 | K31: 547911 | L31: 349350
A32: Запасы | B32: 22570 | C32: 19314 | D32: 38038 | E32: 68442
A33: Предоплаченные расходы | B33: 10434 | C33: 8436 | D33: 21567 | E33: 30804
A34: Текущий налог на прибыль | B34: 2812 | C34: 1480 | D34: 3731 | E34: 2958 | H34: ПРОЧИЙ СОВОКУПНЫЙ ДОХОД
A35: Прочие оборотные активы | B35: 9250 | C35: 5920 | D35: 9919 | E35: 23664
A36: ИТОГО ОБОРОТНЫЕ АКТИВЫ | B36: 309172 | C36: 365412 | D36: 782145 | E36: 988686 | H36: Статьи, которые могут быть впоследствии переклассифицированы в прибыль или убыток | I36: -46990 | J36: 38332 | K36: -11466 | L36: 34986
H37: Курсовые разницы | I37: -1258 | J37: -5476 | K37: 6643 | L37: 714
A38: ИТОГО АКТИВЫ | B38: 1889220 | C38: 1963738 | D38: 3246061 | E38: 4046748 | H38: Убытки от переоценки FVOCI | I38: 296 | J38: -814 | K38: 3185 | L38: -306
H39: Прибыль / убыток от переоценки хеджинговых инструментов, используемых для хеджирования денежных потоков | I39: -56684 | J39: 54612 | K39: -25298 | L39: 42942
H40: Прибыль / убыток от переоценки хеджинговых инструментов инвестиций, учитываемых методом долевого участия, используемых для хеджирования денежных потоков | I40: -814 | J40: 962 | K40: -819 | L40: 1530
A41: ОБЯЗАТЕЛЬСТВА И КАПИТАЛ | H41: Налог, относящийся к прочему совокупному доходу | I41: 11470 | J41: -10952 | K41: 4823 | L41: -9894
H42: Статьи, которые не будут переклассифицированы в прибыль или убыток | I42: -740 | J42: -1702 | K42: -4186 | L42: -1020
A43: КАПИТАЛ | H43: Актуарные убытки по пенсионным обязательствам | I43: -962 | J43: -2146 | K43: -5096 | L43: -1224
A44: Уставный капитал | B44: 118178 | C44: 118178 | D44: 145327 | E44: 162894 | H44: Налог, относящийся к прочему совокупному доходу | I44: 222 | J44: 444 | K44: 910 | L44: 204
A45: Статьи, которые не будут переклассифицированы в прибыль или убыток | H45: ПРОЧИЙ СОВОКУПНЫЙ ДОХОД / РАСХОД ЗА ГОД | I45: -47730 | J45: 36630 | K45: -15652 | L45: 33966
A46: Казначейские акции | B46: - | C46: - | D46: -3003 | E46: -3978
A47: Актуарные убытки по обязательствам по выплате пенсий | B47: -3552 | C47: -5254 | D47: -24934 | E47: -28968 | H47: СОВОКУПНЫЙ ДОХОД / РАСХОД ЗА ГОД | I47: -109594 | J47: 107596 | K47: 532259 | L47: 383316
A48: Статьи, которые могут быть переклассифицированы в прибыль или убыток | H48: Базовая прибыль / убыток на акцию (в российских рублях) | I48: -0.4514 | J48: 0.5106 | K48: 3.9676 | L48: 2.5296
A49: Курсовые разницы по зарубежным операциям | B49: -14874 | C49: -20350 | D49: -20111 | E49: -21828 | H49: Разводненная прибыль / убыток на акцию (в российских рублях) | I49: -0.4514 | J49: 0.5106 | K49: 3.9676 | L49: 2.5296
A50: Прибыль от переоценки хеджинговых инструментов, заключенных для хеджирования денежных потоков | B50: -33300 | C50: 11174 | D50: 25571 | E50: 63240
A51: Прибыль/убыток от переоценки FVOCI | B51: 148 | C51: -518 | D51: 1911 | E51: 1836
A52: Резервы с ограничениями | B52: 5328 | C52: 5624 | D52: 6279 | E52: 7650 | H52: ИСТОЧНИКИ
A53: Нераспределенная прибыль прошлых лет | B53: 388204 | C53: 326044 | D53: 736827 | E53: 1439424 | H53: ОФП: https://investor.turkishairlines.com/en/financial-and-operational/financial-results?page=1&year=-&term=12-month (отчётности в USD) - стр.9-10 (2020 гг.), стр.8-9 (остальные)
A54: Чистый убыток / прибыль за год | B54: -61864 | C54: 70966 | D54: 547911 | E54: 349350 | H54: ОПУ: https://investor.turkishairlines.com/en/financial-and-operational/financial-results?page=1&year=-&term=12-month (отчётности в USD) - стр.11 (2020 г.), стр.10 (остальные)
A55: Капитал материнской компании | B55: 398268 | C55: 505864 | D55: 1415778 | E55: 1969620
A56: Неконтролирующие доли | B56: 74 | C56: 74 | D56: 455 | E56: 408 | H56: Используемый курс доллара для рассчётов | I56: 74 руб./доллар | J56: 74 руб./доллар | K56: 91 руб./доллар | L56: 102 руб./доллар
A57: ИТОГО КАПИТАЛ | B57: 398342 | C57: 505938 | D57: 1416233 | E57: 1970028 | H57: Источник: Центральный банк Российской Федерации https://www.cbr.ru/currency_base/dynamics/
A59: ДОЛГОСРОЧНЫЕ ОБЯЗАТЕЛЬСТВА
A60: Долгосрочные займы | B60: 198394 | C60: 172642 | D60: 42952 | E60: 3366
A61: Долгосрочные обязательства по аренде | B61: 708846 | C61: 634476 | D61: 914732 | E61: 1034178
A62: Прочая кредиторская задолженность
A63: Третьи стороны | B63: 1628 | C63: 4070 | D63: 2275 | E63: 3264
A64: Отложенные доходы | B64: 8066 | C64: 6808 | D64: 9828 | E64: 13362
A65: Долгосрочные резервы
A66: Резервы на выплаты сотрудникам | B66: 9916 | C66: 8362 | D66: 20839 | E66: 25194
A67: Прочие резервы | B67: 3626 | C67: 3404 | D67: 7735 | E67: 10914
A68: Отложенное налоговое обязательство | B68: 82806 | C68: 126836 | D68: 4550 | E68: 6630
A69: ИТОГО ДОЛГОСРОЧНЫЕ ОБЯЗАТЕЛЬСТВА | B69: 1013282 | C69: 956598 | D69: 1002911 | E69: 1096908
A71: КРАТКОСРОЧНЫЕ ОБЯЗАТЕЛЬСТВА
A72: Краткосрочные займы | B72: 112998 | C72: 65342 | D72: 122395 | E72: 160242
A73: Краткосрочная часть долгосрочных займов | B73: 87764 | C73: 106782 | D73: 56238 | E73: 29682
A74: Краткосрочная часть обязательств по аренде | B74: 127872 | C74: 123580 | D74: 160160 | E74: 186354
A75: Прочие финансовые обязательства | B75: 1258 | C75: 592 | D75: - | E75: -
A76: Кредиторская задолженность
A77: Аффилированные лица | B77: 10434 | C77: 12358 | D77: 25935 | E77: 29886
A78: Третьи стороны | B78: 53280 | C78: 53576 | D78: 91546 | E78: 122502
A79: Обязательства по выплатам сотрудникам | B79: 6660 | C79: 7770 | D79: 38038 | E79: 54672
A80: Прочая кредиторская задолженность
A81: Аффилированные лица | B81: - | C81: 370 | D81: 364 | E81: 102
A82: Третьи стороны | B82: 6512 | C82: 12506 | D82: 21658 | E82: 32130
A83: Производные финансовые инструменты | B83: 4736 | C83: 2072 | D83: 9191 | E83: 3774
A84: Отложенные доходы | B84: 45436 | C84: 93536 | D84: 246155 | E84: 300288
A85: Краткосрочные резервы
A86: Текущий налоговый резерв | B86: - | C86: 1184 | D86: 3549 | E86: -
A87: Резервы на выплаты сотрудникам | B87: 1184 | C87: 1332 | D87: 4550 | E87: 10302
A88: Прочие резервы | B88: 740 | C88: 592 | D88: 546 | E88: 1428
A89: Прочие краткосрочные обязательства | B89: 18722 | C89: 19610 | D89: 46592 | E89: 48450
A90: ИТОГО КРАТКОСРОЧНЫЕ ОБЯЗАТЕЛЬСТВА | B90: 477596 | C90: 501202 | D90: 826917 | E90: 979812
A92: ИТОГО ОБЯЗАТЕЛЬСТВА И КАПИТАЛ | B92: 1889220 | C92: 1963738 | D92: 3246061 | E92: 4046748
A95: Метрики
A97: Ликвидность
A98: Текущая | B98: =TurkishAirlines!B36/TurkishAirlines!B90 -> 0.64735048 | C98: =TurkishAirlines!C36/TurkishAirlines!C90 -> 0.72907131 | D98: =TurkishAirlines!D36/TurkishAirlines!D90 -> 0.94585672 | E98: =TurkishAirlines!E36/TurkishAirlines!E90 -> 1.0090568
A99: Быстрая | B99: =(TurkishAirlines!B36-TurkishAirlines!B32)/TurkishAirlines!B90 -> 0.60009297 | C99: =(TurkishAirlines!C36-TurkishAirlines!C32)/TurkishAirlines!C90 -> 0.69053595 | D99: =(TurkishAirlines!D36-TurkishAirlines!D32)/TurkishAirlines!D90 -> 0.89985694 | E99: =(TurkishAirlines!E36-TurkishAirlines!E32)/TurkishAirlines!E90 -> 0.93920466
A100: Абсолютная | B100: =(TurkishAirlines!B23+TurkishAirlines!B24)/TurkishAirlines!B90 -> 0.28339015 | C100: =(TurkishAirlines!C23+TurkishAirlines!C24)/TurkishAirlines!C90 -> 0.39598405 | D100: =(TurkishAirlines!D23+TurkishAirlines!D24)/TurkishAirlines!D90 -> 0.6632552 | E100: =(TurkishAirlines!E23+TurkishAirlines!E24)/TurkishAirlines!E90 -> 0.63158443
A102: Финансовая устойчивость
A103: Коэффициент автономии | B103: =TurkishAirlines!B57/TurkishAirlines!B38 -> 0.21084998 | C103: =TurkishAirlines!C57/TurkishAirlines!C38 -> 0.25764028 | D103: =TurkishAirlines!D57/TurkishAirlines!D38 -> 0.43629279 | E103: =TurkishAirlines!E57/TurkishAirlines!E38 -> 0.48681756
A104: Коэффициент соотношения заемных и собственных средств | B104: =(TurkishAirlines!B69+TurkishAirlines!B90)/TurkishAirlines!B57 -> 3.7427085 | C104: =(TurkishAirlines!C69+TurkishAirlines!C90)/TurkishAirlines!C57 -> 2.8813807 | D104: =(TurkishAirlines!D69+TurkishAirlines!D90)/TurkishAirlines!D57 -> 1.2920388 | E104: =(TurkishAirlines!E69+TurkishAirlines!E90)/TurkishAirlines!E57 -> 1.0541576
A105: Коэффициент финансового левериджа | B105: =1/TurkishAirlines!B103 -> 4.7427085 | C105: =1/TurkishAirlines!C103 -> 3.8813807 | D105: =1/TurkishAirlines!D103 -> 2.2920388 | E105: =1/TurkishAirlines!E103 -> 2.0541576
A107: Коэффициенты деловой активности
A108: Оборачиваемость активов | B108: - | C108: =TurkishAirlines!J6/((TurkishAirlines!C38+TurkishAirlines!B38)/2) -> 0.41047112 | D108: =TurkishAirlines!K6/((TurkishAirlines!D38+TurkishAirlines!C38)/2) -> 0.73159137 | E108: =TurkishAirlines!L6/((TurkishAirlines!E38+TurkishAirlines!D38)/2) -> 0.63411451
A109: Оборачиваемость дебиторской задолженности | B109: - | C109: =TurkishAirlines!J6/((TurkishAirlines!C10+TurkishAirlines!B10+TurkishAirlines!C26+TurkishAirlines!C27+TurkishAirlines!B26+TurkishAirlines!B27+TurkishAirlines!C29+TurkishAirlines!C30+TurkishAirlines!B29+TurkishAirlines!B30)/2) -> 3.8675353 | D109: =TurkishAirlines!K6/((TurkishAirlines!D10+TurkishAirlines!C10+TurkishAirlines!D26+TurkishAirlines!D27+TurkishAirlines!C26+TurkishAirlines!C27+TurkishAirlines!D29+TurkishAirlines!D30+TurkishAirlines!C29+TurkishAirlines!C30)/2) -> 7.9862295 | E109: =TurkishAirlines!L6/((TurkishAirlines!E9+TurkishAirlines!E10+TurkishAirlines!D10+TurkishAirlines!E26+TurkishAirlines!E27+TurkishAirlines!D26+TurkishAirlines!D27+TurkishAirlines!E29+TurkishAirlines!E30+TurkishAirlines!D29+TurkishAirlines!D30)/2) -> 7.1529402
...

Sheet Ютэер
A1: Отчет о финансовом положении | I1: Отчет о прибылях и убытках
A2: на 31 декабря 202X года в миллионах рублей | I2: на 31 декабря 202X года в миллионах рублей
B3: 2020 г. | C3: 2021 г. | D3: 2023 г. | E3: 2024г. | J3: 2020 г. | K3: 2021 г. | L3: 2023 г. | M3: 2024 г.
A4: АКТИВЫ | I4: Выручка от пассажирских перевозок и вертолетных работ | J4: 55199 | K4: 75544 | L4: 97671 | M4: 111449
A5: Внеоборотные активы | I5: Выручка от прочей реализации | J5: 838 | K5: 1207 | L5: 1984 | M5: 1895
A6: Основные средства | B6: 26627 | C6: 30187 | D6: 58662 | E6: 62334 | I6: Выручка | J6: 56037 | K6: 76752 | L6: 99655 | M6: 113344
A7: Активы в форме права пользования | B7: 33577 | C7: 36306 | D7: 24210 | E7: 25161 | I7: Операционные расходы и доходы
A8: Нематериальные активы | B8: 56 | C8: 83 | D8: 40 | E8: 35 | I8: Прямые операционные расходы | J8: -25772 | K8: -37717 | L8: -52464 | M8: -60911
A9: Авансы под поставку основных средств и активов в форме права пользования | B9: 1391 | C9: 1474 | D9: 2442 | E9: 1401 | I9: Расходы на персонал | J9: -14920 | K9: -16821 | L9: -20176 | M9: -23060
A10: Долгосрочные финансовые активы | B10: 160 | C10: 2755 | D10: 8562 | E10: 9874 | I10: Износ и амортизация основных средств и активов в форме права пользования | J10: -8384 | K10: -7545 | L10: -14509 | M10: -18201
A11: Инвестиции в компании, учитываемые методом долевого участия | B11: 486 | C11: 404 | D11: 792 | E11: 82 | I11: Затраты на ремонт | J11: -2954 | K11: -4112 | L11: -2618 | M11: -2654
A12: Финансовые активы, оцениваемые по справедливой стоимости через прибыль или убыток | B12: 4 | C12: - | D12: - | E12: - | I12: Комиссионные вознаграждения | J12: -916 | K12: -1118 | L12: -936 | M12: -867
A13: Торговая и прочая дебиторская задолженность | B13: 764 | C13: 69 | D13: 393 | E13: 521 | I13: Государственные субсидии | J13: 3848 | K13: 2638 | L13: 3796 | M13: 3390
A14: Обеспечительные депозиты по аренде воздушных судов | B14: 280 | C14: 333 | D14: - | E14: - | I14: Операции по продаже и обратной аренде | J14: 134 | K14: 129 | L14: 4 | M14: 4
A15: Авансы выданные | B15: 7 | C15: 6 | D15: 53 | E15: 427 | I15: Прочие доходы | J15: 190 | K15: 578 | L15: 229 | M15: 181
A16: Итого внеоборотные активы | B16: 63350 | C16: 71618 | D16: 95156 | E16: 99834 | I16: Прочие расходы | J16: -3018 | K16: -3209 | L16: -2863 | M16: -2879
J17: -51791 | K17: -67177 | L17: -89537 | M17: -104996
I18: Результаты операционной деятельности | J18: 4245 | K18: 9575 | L18: 10118 | M18: 8348
A19: Оборотные активы
A20: Запасы | B20: 2122 | C20: 3436 | D20: 5666 | E20: 10221 | I20: Нетто-величина прибыли от изменения обменных курсов иностранных валют | J20: -2106 | K20: -8 | L20: -956 | M20: -2639
A21: Торговая и прочая дебиторская задолженность | B21: 3675 | C21: 5498 | D21: 6694 | E21: 6956 | I21: Резерв под ожидаемые кредитные убытки | J21: -656 | K21: -217 | L21: -1234 | M21: -486
A22: Затраты по договору | B22: 30 | C22: 92 | D22: 106 | E22: 139 | I22: Обесценивание авансов выданных | J22: - | K22: - | L22: -225 | M22: -839
A23: Авансы выданные | B23: 1058 | C23: 1761 | D23: 4892 | E23: 4376 | I23: Доля в прибыли (убытке) ассоциированных компаний | J23: -9 | K23: 231 | L23: 307 | M23: 316
A24: Налоги к возмещению | B24: 1865 | C24: 3585 | D24: 3643 | E24: 2970 | I24: Восстановление (списание) запасов до возможной стоимости реализации | J24: -222 | K24: 1195 | L24: 314 | M24: 11
A25: Дебиторская задолженность по налогу на прибыль | B25: 82 | C25: 353 | D25: 39 | E25: 23 | I25: Прибыль (убыток) от выбытия основных средств | J25: -142 | K25: 158 | L25: -210 | M25: -277
A26: Обеспечительные депозиты по аренде воздушных судов | B26: - | C26: 83 | D26: - | E26: - | I26: Убыток от обесценивания внеоборотных активов | J26: - | K26: - | L26: - | M26: -3171
A27: Краткосрочные финансовые активы | B27: 1245 | C27: 1463 | D27: 1429 | E27: 170 | I27: Результат от переоценки и обесценения активов | J27: -5902 | K27: -10 | L27: - | M27: -
A28: Денежные средства и их эквиваленты | B28: 12679 | C28: 7569 | D28: 5537 | E28: 5337 | I28: (Убыток) прибыль от расторжения договоров аренды | J28: 100 | K28: -83412 | L28: 124 | M28: -2
A29: Итого оборотные активы | B29: 22756 | C29: 23840 | D29: 28007 | E29: 30191 | I29: Прибыль от реструктуризации финансовых обязательств | J29: 14399 | K29: 28531 | L29: - | M29: -
A30: Активы, удерживаемые для продажи | B30: - | C30: - | D30: - | E30: 324 | I30: Финансовые доходы | J30: 695 | K30: 442 | L30: 1294 | M30: 1231
I31: Финансовые расходы | J31: -6673 | K31: -5865 | L31: -5936 | M31: -7553
A32: Всего активы | B32: 86106 | C32: 95458 | D32: 123163 | E32: 130350 | I32: Прибыль до налогообложения | J32: 3671 | K32: 33950 | L32: 3596 | M32: -5062
A33: Собственный капитал | I33: Расход по налогу на прибыль | J33: -542 | K33: -7125 | L33: -809 | M33: -1954
A34: Акционерный капитал | B34: 3702 | C34: 7896 | D34: 7896 | E34: 7896 | I34: Прибыль (убыток) за год | J34: 3130 | K34: 26825 | L34: 2786 | M34: -7015
A35: Эмиссионный доход | B35: 21875 | C35: 31311 | D35: 31311 | E35: 31311
A36: Собственные выкупленные акции | B36: -1352 | C36: -7402 | D36: -7402 | E36: -7402
A37: Резерв курсовых разниц при пересчете из других валют | B37: 334 | C37: 417 | D37: -825 | E37: -1431 | I37: ИСТОЧНИКИ
A38: Резерв на переоценку основных средств и активов в форме права пользования | B38: 17849 | C38: 17912 | D38: 21779 | E38: 20492 | I38: Очет о прибылях и убытках - | J38: https://smart-lab.ru/q/UTAR/f/y/MSFO/
A39: Результат оценки актуарных обязательств | B39: -31 | C39: -63 | D39: 91 | E39: 121 | I39: Отчет о финансовом положении - | J39: https://smart-lab.ru/q/UTAR/f/y/MSFO/
A40: Непокрытый убыток | B40: -67980 | C40: -39918 | D40: -30499 | E40: -37135
A41: Итого собственный капитал, принадлежащий акционерам Компании | B41: -25602 | C41: 10154 | D41: 22353 | E41: 13851
A43: Доля неконтролирующих акционеров | B43: 676 | C43: 647 | D43: 714 | E43: 593
A44: Итого собственный капитал | B44: -4925 | C44: 10801 | D44: 23067 | E44: 14445
A46: Долгосрочные обязательства
A47: Кредиты и займы | B47: 12714 | C47: 19563 | D47: 27881 | E47: 26716
A48: Обязательства по аренде | B48: 17130 | C48: 24306 | D48: 21000 | E48: 23954
A49: Торговая и прочая кредиторская задолженность | B49: 11 | C49: - | D49: - | E49: -
A50: Доходы будущих периодов | B50: 490 | C50: 362 | D50: 22942 | E50: 19
A51: Отложенная выручка по программе лояльности часто летающих пассажиров | B51: 863 | C51: 649 | D51: 395706 | E51: -
A52: Авансы, полученные от покупателей и заказчиков | B52: 19 | C52: - | D52: 511015 | E52: -
A53: Задолженность по прочим налогам и сборам | B53: 287 | C53: 249 | D53: 12113 | E53: -
A54: Обязательства по пособиям по окончании трудовой деятельности | B54: 290 | C54: 347 | D54: 247123 | E54: 256
A55: Отложенные налоговые обязательства | B55: 4936 | C55: 12055 | D55: 13793 | E55: 16737
A56: Итого долгосрочные обязательства | B56: 36742 | C56: 57531 | D56: 63353 | E56: 67681
A58: Краткосрочные обязательства
A59: Кредиты и займы | B59: 48782 | C59: 5589 | D59: 2863 | E59: 4393
A60: Обязательства по аренде | B60: 10470 | C60: 7358 | D60: 16290 | E60: 22542
A61: Производные финансовые инструменты | B61: 96 | C61: 102 | D61: - | E61: -
A62: Торговая и прочая кредиторская задолженность | B62: 9044 | C62: 9356 | D62: 11551 | E62: 14359
A63: Доходы будущих периодов и прочие нефинансовые обязательства | B63: 130 | C63: 130 | D63: 4 | E63: 4
A64: Обязательства по договорам – пассажирские перевозки | B64: 2636 | C64: 2789 | D64: 3425 | E64: 4113
A65: Авансы, полученные от покупателей и заказчиков | B65: 372 | C65: 308 | D65: 511 | E65: 722
A66: Отложенная выручка по программе лояльности часто летающих пассажиров | B66: 313 | C66: 224 | D66: 158 | E66: 493
A67: Кредиторская задолженность по налогу на прибыль | B67: 63 | C67: 5298 | D67: 111 | E67: 18
A68: Задолженность по прочим налогам и сборам | B68: 2310 | C68: 1183 | D68: 1735 | E68: 1445
A69: Оценочные обязательства | B69: 74 | C69: 82773 | D69: 90 | E69: 130
A70: Обязательства по пособиям по окончании трудовой деятельности | B70: 1 | C70: 1 | D70: 4 | E70: 4
A72: Итого краткосрочные обязательства | B72: 74290 | C72: 27125 | D72: 36743 | E72: 48223
A73: Итого обязательства | B73: 111032 | C73: 84657 | D73: 100096 | E73: 115904
A74: Итого собственный капитал и обязательства | B74: 86106 | C74: 95458 | D74: 123163 | E74: 130350
A81: Метрики
A83: Ликвидность
A84: Текущая | B84: ='Ютэер'!B29/'Ютэер'!B72 -> 0.3063131 | C84: ='Ютэер'!C29/'Ютэер'!C72 -> 0.87889401 | D84: ='Ютэер'!D29/'Ютэер'!D72 -> 0.76224043 | E84: ='Ютэер'!E29/'Ютэер'!E72 -> 0.62607055
A85: Быстрая | B85: =('Ютэер'!B28+'Ютэер'!B62+'Ютэер'!B27)/'Ютэер'!B73 -> 0.20685928 | C85: =('Ютэер'!C28+'Ютэер'!C62+'Ютэер'!C27)/'Ютэер'!C73 -> 0.2172059 | D85: =('Ютэер'!D28+'Ютэер'!D62+'Ютэер'!D27)/'Ютэер'!D73 -> 0.18499241 | E85: =('Ютэер'!E28+'Ютэер'!E62+'Ютэер'!E27)/'Ютэер'!E73 -> 0.17140047
A86: Абсолютная | B86: ='Ютэер'!B28/'Ютэер'!B72 -> 0.170669 | C86: ='Ютэер'!C28/'Ютэер'!C72 -> 0.27904147 | D86: ='Ютэер'!D28/'Ютэер'!D72 -> 0.15069537 | E86: ='Ютэер'!E28/'Ютэер'!E72 -> 0.11067333
A88: Финансовая устойчивость
A89: Коэффициент автономии | B89: =abs('Ютэер'!B44)/(abs('Ютэер'!B44)+'Ютэер'!B73) -> 0.042472641 | C89: =abs('Ютэер'!C44)/(abs('Ютэер'!C44)+'Ютэер'!C73) -> 0.11314924 | D89: =abs('Ютэер'!D44)/(abs('Ютэер'!D44)+'Ютэер'!D73) -> 0.18728839 | E89: =abs('Ютэер'!E44)/(abs('Ютэер'!E44)+'Ютэер'!E73) -> 0.11081788
A90: Коэффициент соотношения заемных и собственных средств | B90: ='Ютэер'!B73/'Ютэер'!B44 -> -22.544569 | C90: ='Ютэер'!C73/'Ютэер'!C44 -> 7.8378854 | D90: ='Ютэер'!D73/'Ютэер'!D44 -> 4.3393593 | E90: ='Ютэер'!E73/'Ютэер'!E44 -> 8.0238145
A91: Коэффициент финансового левериджа | B91: ='Ютэер'!B32/'Ютэер'!B44 -> -17.483452 | C91: ='Ютэер'!C32/'Ютэер'!C44 -> 8.8378854 | D91: ='Ютэер'!D32/'Ютэер'!D44 -> 5.3393593 | E91: ='Ютэер'!E32/'Ютэер'!E44 -> 9.0238837
A93: Коэффициенты деловой активности
A94: Оборачиваемость активов | B94: =('Ютэер'!J6)/(('Ютэер'!B108+'Ютэер'!B32)/2) -> 1.0853048 | C94: =('Ютэер'!K6)/(('Ютэер'!B32+'Ютэер'!C32)/2) -> 0.84545394 | D94: =('Ютэер'!L6)/(('Ютэер'!C32+'Ютэер'!D32)/2) -> 0.91166905 | E94: =('Ютэер'!M6)/(('Ютэер'!D32+'Ютэер'!E32)/2) -> 0.89418689
A95: Оборачиваемость дебиторской задолженности | B95: =(((('Ютэер'!B109+'Ютэер'!B110)+('Ютэер'!B21+'Ютэер'!B25))/2)*365)/'Ютэер'!J6 -> 37.873057 | C95: =(((('Ютэер'!B21+'Ютэер'!B25)+('Ютэер'!C21+'Ютэер'!C25))/2)*365)/'Ютэер'!K6 -> 22.845789 | D95: =(((('Ютэер'!C21+'Ютэер'!C25)+('Ютэер'!D21+'Ютэер'!D25))/2)*365)/'Ютэер'!L6 -> 23.045306 | E95: =(((('Ютэер'!D21+'Ютэер'!D25)+('Ютэер'!E21+'Ютэер'!E25))/2)*365)/'Ютэер'!M6 -> 22.078275
A97: Коэффициенты рентабельности
A98: Рентабельность продаж (ROS) | B98: =(('Ютэер'!J34)*100/'Ютэер'!J6) -> 5.5855952 | C98: =(('Ютэер'!K34)*100/'Ютэер'!K6) -> 34.950229 | D98: =(('Ютэер'!L34)*100/'Ютэер'!L6) -> 2.795645 | E98: =(('Ютэер'!M34)*100/'Ютэер'!M6) -> -6.1891234
A99: Рентабельность активов (ROA) | B99: =('Ютэер'!J34)*100/(('Ютэер'!B108+'Ютэер'!B32)/2) -> 6.0620733 | C99: =('Ютэер'!K34)*100/(('Ютэер'!B32+'Ютэер'!C32)/2) -> 29.548809 | D99: =('Ютэер'!L34)*100/(('Ютэер'!C32+'Ютэер'!D32)/2) -> 2.548703 | E99: =('Ютэер'!M34)*100/(('Ютэер'!D32+'Ютэер'!E32)/2) -> -5.534233
A100: Рентабельность собственного капитала (ROE) | B100: =('Ютэер'!J34)*100/(('Ютэер'!B44+'Ютэер'!B113)/2) -> 19.930593 | C100: =('Ютэер'!K34)*100/(('Ютэер'!B44+'Ютэер'!C44)/2) -> 913.03608 | D100: =('Ютэер'!L34)*100/(('Ютэер'!C44+'Ютэер'!D44)/2) -> 16.452108 | E100: =('Ютэер'!M34)*100/(('Ютэер'!D44+'Ютэер'!E44)/2) -> -37.401365
A107: Метрики за 2019 год
A108: Итоговые активы | B108: 17159
A109: Торговая и прочая дебиторская задолженность | B109: 7709
A110: Дебиторская задолженность по налогу на прибыль | B110: 163
A113: Итого капитал | B113: 36334

Sheet Метрики
A1: Метрики
B2: 2020 г. | C2: 2021 г. | D2: 2023 г. | E2: 2024 г. | F2: 2020 г. | G2: 2021 г. | H2: 2023 г. | I2: 2024 г. | J2: 2020 г. | K2: 2021 г. | L2: 2023 г. | M2: 2024 г.
B3: Аэрофлот | F3: Utair | J3: TurkishAirlines
A4: Ликвидность
A5: Текущая | B5: ='Аэрофлот'!B13/'Аэрофлот'!B41 -> 0.65798745 | C5: ='Аэрофлот'!C13/'Аэрофлот'!C41 -> 0.69828459 | D5: ='Аэрофлот'!D13/'Аэрофлот'!D41 -> 0.73851309 | E5: ='Аэрофлот'!E13/'Аэрофлот'!E41 -> 0.62028528 | F5: 0.3063131 | G5: 0.87889401 | H5: 0.76224043 | I5: 0.62607055 | J5: 0.64735048 | K5: 0.72907131 | L5: 0.94585672 | M5: 1.0090568
A6: Быстрая | B6: =('Аэрофлот'!B6+'Аэрофлот'!B7+'Аэрофлот'!B8)/'Аэрофлот'!B41 -> 0.57175463 | C6: =('Аэрофлот'!C6+'Аэрофлот'!C7+'Аэрофлот'!C8)/'Аэрофлот'!C41 -> 0.61252146 | D6: =('Аэрофлот'!D6+'Аэрофлот'!D7+'Аэрофлот'!D8)/'Аэрофлот'!D41 -> 0.58711912 | E6: =('Аэрофлот'!E6+'Аэрофлот'!E7+'Аэрофлот'!E8)/'Аэрофлот'!E41 -> 0.47152897 | F6: 0.20685928 | G6: 0.2172059 | H6: 0.18499241 | I6: 0.17140047 | J6: 0.60009297 | K6: 0.69053595 | L6: 0.89985694 | M6: 0.93920466
A7: Абсолютная | B7: =('Аэрофлот'!B6+'Аэрофлот'!B7)/'Аэрофлот'!B41 -> 0.33338073 | C7: =('Аэрофлот'!C6+'Аэрофлот'!C7)/'Аэрофлот'!C41 -> 0.34393664 | D7: =('Аэрофлот'!D6+'Аэрофлот'!D7)/'Аэрофлот'!D41 -> 0.34488993 | E7: =('Аэрофлот'!E6+'Аэрофлот'!E7)/'Аэрофлот'!E41 -> 0.25774877 | F7: 0.170669 | G7: 0.27904147 | H7: 0.15069537 | I7: 0.11067333 | J7: 0.28339015 | K7: 0.39598405 | L7: 0.6632552 | M7: 0.63158443
A9: Финансовая устойчивость
A10: Коэффициент автономии | B10: =abs('Аэрофлот'!B65)/(abs('Аэрофлот'!B65)+'Аэрофлот'!B52) -> 0.092506512 | C10: =abs('Аэрофлот'!C65)/(abs('Аэрофлот'!C65)+'Аэрофлот'!C52) -> 0.10442508 | D10: =abs('Аэрофлот'!D65)/(abs('Аэрофлот'!D65)+'Аэрофлот'!D52) -> 0.07529725 | E10: =abs('Аэрофлот'!E65)/(abs('Аэрофлот'!E65)+'Аэрофлот'!E52) -> 0.055685964 | F10: 0.042472641 | G10: 0.11314924 | H10: 0.18728839 | I10: 0.11081788 | J10: 0.21084998 | K10: 0.25764028 | L10: 0.43629279 | M10: 0.48681756
A11: Коэффициент соотношения заемных и собственных средств | B11: =('Аэрофлот'!B41+'Аэрофлот'!B50)/'Аэрофлот'!B65 -> -9.8100498 | C11: =('Аэрофлот'!C41+'Аэрофлот'!C50)/'Аэрофлот'!C65 -> -8.5762439 | D11: =('Аэрофлот'!D41+'Аэрофлот'!D50)/'Аэрофлот'!D65 -> -12.280697 | E11: =('Аэрофлот'!E41+'Аэрофлот'!E50)/'Аэрофлот'!E65 -> -16.957847 | F11: -22.544569 | G11: 7.8378854 | H11: 4.3393593 | I11: 8.0238145 | J11: 3.7427085 | K11: 2.8813807 | L11: 1.2920388 | M11: 1.0541576
A12: Коэффициент финансового левериджа | B12: ='Аэрофлот'!B28/'Аэрофлот'!B65 -> -8.8100498 | C12: ='Аэрофлот'!C28/'Аэрофлот'!C65 -> -7.5762439 | D12: ='Аэрофлот'!D28/'Аэрофлот'!D65 -> -11.280697 | E12: ='Аэрофлот'!E28/'Аэрофлот'!E65 -> -15.957847 | F12: -17.483452 | G12: 8.8378854 | H12: 5.3393593 | I12: 9.0238837 | J12: 4.7427085 | K12: 3.8813807 | L12: 2.2920388 | M12: 2.0541576
A14: Коэффициенты деловой активности
A15: Оборачиваемость активов | B15: =('Аэрофлот'!J6)/(('Аэрофлот'!B119+'Аэрофлот'!B28)/2) -> 0.31000625 | C15: =('Аэрофлот'!K6)/(('Аэрофлот'!C119+'Аэрофлот'!C28)/2) -> 0.88644463 | D15: =('Аэрофлот'!L6)/(('Аэрофлот'!D119+'Аэрофлот'!D28)/2) -> 1.0990777 | E15: =('Аэрофлот'!M6)/(('Аэрофлот'!E119+'Аэрофлот'!E28)/2) -> 1.4811789 | F15: 1.0853048 | G15: 0.84545394 | H15: 0.91166905 | I15: 0.89418689 | J15: - | K15: 0.41047112 | L15: 0.73159137 | M15: 0.63411451
A16: Оборачиваемость дебиторской задолженности (в днях) | B16: =(('Аэрофлот'!B120+'Аэрофлот'!B8)/2)*365/('Аэрофлот'!J6) -> 98.755171 | C16: =(('Аэрофлот'!B8+'Аэрофлот'!C8)*365/2)/('Аэрофлот'!K6) -> 52.057072 | D16: =(('Аэрофлот'!C8+'Аэрофлот'!D8)/2)*365/('Аэрофлот'!L6) -> 46.348359 | E16: =(('Аэрофлот'!D8+'Аэрофлот'!E8)/2)*365/('Аэрофлот'!M6) -> 36.149606 | F16: 37.873057 | G16: 22.845789 | H16: 23.045306 | I16: 22.078275 | J16: - | K16: 94.375351 | L16: 45.70367 | M16: 51.027967
A18: Коэффициенты рентабельности
A19: Рентабельность продаж (ROS) % | B19: ='Аэрофлот'!J24*100/'Аэрофлот'!J6 -> -40.772779 | C19: ='Аэрофлот'!K24*100/'Аэрофлот'!K6 -> -7.0078681 | D19: ='Аэрофлот'!L24*100/'Аэрофлот'!L6 -> -2.2902871 | E19: ='Аэрофлот'!M24*100/'Аэрофлот'!M6 -> 6.4216811 | F19: 5.5855952 | G19: 34.950229 | H19: 2.795645 | I19: -6.1891234 | J19: -12.414612 | K19: 8.974359 | L19: 28.750836 | M19: 15.108739
A20: Рентабельность активов (ROA) % | B20: ='Аэрофлот'!J24*100/(('Аэрофлот'!B119+'Аэрофлот'!B28)/2) -> -12.639816 | C20: ='Аэрофлот'!K24*100/(('Аэрофлот'!B28+'Аэрофлот'!C28)/2) -> -3.2422963 | D20: ='Аэрофлот'!L24*100/(('Аэрофлот'!C28+'Аэрофлот'!D28)/2) -> -1.2611853 | E20: ='Аэрофлот'!M24*100/(('Аэрофлот'!D28+'Аэрофлот'!E28)/2) -> 4.8456346 | F20: 6.0620733 | G20: 29.548809 | H20: 2.548703 | I20: -5.534233 | J20: - | K20: 3.6837152 | L20: 21.033863 | M20: 9.5806705
A21: Рентабельность собственного капитала (ROE) % | B21: - | C21: =('Аэрофлот'!K24)*100/(('Аэрофлот'!B65+'Аэрофлот'!C65)/2) -> 26.327048 | D21: =('Аэрофлот'!L24)*100/(('Аэрофлот'!C65+'Аэрофлот'!D65)/2) -> 11.436752 | E21: =('Аэрофлот'!M24)*100/(('Аэрофлот'!D65+'Аэрофлот'!E65)/2) -> -64.256559 | F21: 19.930593 | G21: 913.03608 | H21: 16.452108 | I21: -37.401365 | J21: - | K21: 15.695581 | L21: 57.0096 | M21: 20.633377

Sheet Горизонтальный анализ
A1: Горизонтальный анализ (Аэрофлот) ОФП | F1: Изменения (базовый год 2020)
F2: Абсолютные отклонения | G2: Относительные отклонения | I2: Абсолютные отклонения | J2: Относительные отклонения | L2: Абсолютные отклонения | M2: Относительные отклонения
A3: на 31 декабря 202X года в миллионах рублей, если не указано иное | G3: Темп роста | H3: Темп прироста | J3: Темп роста | K3: Темп прироста | M3: Темп роста | N3: Темп прироста
B4: 2020 г. | C4: 2021 г. | D4: 2023 г. | E4: 2024 г. | F4: 2021 г. | I4: 2023 г. | L4: 2024 г. | O4: Абсолютные отклонения | P4: Темпы роста | Q4: Темпы прироста
A5: АКТИВЫ
A6: Оборотные активы
A7: Денежные средства и их эквиваленты | B7: 88944 | C7: 74180 | D7: 83117 | E7: 67814 | F7: =(C7-B7) -> -14764 | G7: =(C7/B7) -> 0.83400792 | H7: =(C7-B7)/B7 -> -0.16599208 | I7: =(D7-B7) -> -5827 | J7: =(D7/B7) -> 0.93448687 | K7: =(D7-B7)/B7 -> -0.065513132 | L7: =(E7-B7) -> -21130 | M7: =(E7/B7) -> 0.76243479 | N7: =(E7-B7)/B7 -> -0.23756521 | O7: =IFERROR(__xludf.DUMMYFUNCTION("SPARKLINE({F7; I7; L7},{""charttype"",""line"";""color"",""green""}) "),"") | P7: =IFERROR(__xludf.DUMMYFUNCTION("SPARKLINE({G7; J7; M7},{""charttype"",""column"";""color"",""green""})"),"") | Q7: =IFERROR(__xludf.DUMMYFUNCTION("SPARKLINE({H7;K7;N7},{""charttype"",""line"";""color"",""black""})"),"")
A8: Дебиторская задолженность и предоплаты | B8: 67051 | C8: 73213 | D8: 82262 | E8: 87450 | F8: =(C8-B8) -> 6162 | G8: =(C8/B8) -> 1.0919002 | H8: =(C8-B8)/B8 -> 0.091900195 | I8: =(D8-B8) -> 15211 | J8: =(D8/B8) -> 1.2268572 | K8: =(D8-B8)/B8 -> 0.22685717 | L8: =(E8-B8) -> 20399 | M8: =(E8/B8) -> 1.3042311 | N8: =(E8-B8)/B8 -> 0.30423111 | O8: =IFERROR(__xludf.DUMMYFUNCTION("SPARKLINE({F8; I8; L8},{""charttype"",""line"";""color"",""green""}) "),"") | P8: =IFERROR(__xludf.DUMMYFUNCTION("SPARKLINE({G8; J8; M8},{""charttype"",""column"";""color"",""green""})"),"") | Q8: =IFERROR(__xludf.DUMMYFUNCTION("SPARKLINE({H8;K8;N8},{""charttype"",""line"";""color"",""black""})"),"")
A9: Итого оборотные активы | B9: 185082 | C9: 190344 | D9: 250802 | E9: 253737 | F9: =(C9-B9) -> 5262 | G9: =(C9/B9) -> 1.0284306 | H9: =(C9-B9)/B9 -> 0.028430642 | I9: =(D9-B9) -> 65720 | J9: =(D9/B9) -> 1.3550859 | K9: =(D9-B9)/B9 -> 0.35508585 | L9: =(E9-B9) -> 68655 | M9: =(E9/B9) -> 1.3709437 | N9: =(E9-B9)/B9 -> 0.37094369 | O9: =IFERROR(__xludf.DUMMYFUNCTION("SPARKLINE({F9; I9; L9},{""charttype"",""line"";""color"",""green""}) "),"") | P9: =IFERROR(__xludf.DUMMYFUNCTION("SPARKLINE({G9; J9; M9},{""charttype"",""column"";""color"",""green""})"),"") | Q9: =IFERROR(__xludf.DUMMYFUNCTION("SPARKLINE({H9;K9;N9},{""charttype"",""line"";""color"",""black""})"),"")
A10: Внеоборотные активы
A11: Активы в форме права пользования | B11: 635406 | C11: 725421 | D11: 619883 | E11: 557557 | F11: =(C11-B11) -> 90015 | G11: =(C11/B11) -> 1.1416653 | H11: =(C11-B11)/B11 -> 0.14166533 | I11: =(D11-B11) -> -15523 | J11: =(D11/B11) -> 0.97556995 | K11: =(D11-B11)/B11 -> -0.024430049 | L11: =(E11-B11) -> -77849 | M11: =(E11/B11) -> 0.87748148 | N11: =(E11-B11)/B11 -> -0.12251852 | O11: =IFERROR(__xludf.DUMMYFUNCTION("SPARKLINE({F11; I11; L11},{""charttype"",""line"";""color"",""green""}) "),"") | P11: =IFERROR(__xludf.DUMMYFUNCTION("SPARKLINE({G11; J11; M11},{""charttype"",""column"";""color"",""green""})"),"") | Q11: =IFERROR(__xludf.DUMMYFUNCTION("SPARKLINE({H11;K11;N11},{""charttype"",""line"";""color"",""black""})"),"")
A12: Основные средства | B12: 19825 | C12: 19893 | D12: 104922 | E12: 159838 | F12: =(C12-B12) -> 68 | G12: =(C12/B12) -> 1.00343 | H12: =(C12-B12)/B12 -> 0.0034300126 | I12: =(D12-B12) -> 85097 | J12: =(D12/B12) -> 5.2924086 | K12: =(D12-B12)/B12 -> 4.2924086 | L12: =(E12-B12) -> 140013 | M12: =(E12/B12) -> 8.0624464 | N12: =(E12-B12)/B12 -> 7.0624464 | O12: =IFERROR(__xludf.DUMMYFUNCTION("SPARKLINE({F12; I12; L12},{""charttype"",""line"";""color"",""green""}) "),"") | P12: =IFERROR(__xludf.DUMMYFUNCTION("SPARKLINE({G12; J12; M12},{""charttype"",""column"";""color"",""green""})"),"") | Q12: =IFERROR(__xludf.DUMMYFUNCTION("SPARKLINE({H12;K12;N12},{""charttype"",""line"";""color"",""black""})"),"")
A13: Долгосрочные финансовые инвестиции | B13: 5464 | C13: 5360 | D13: 5335 | E13: 6123 | F13: =(C13-B13) -> -104 | G13: =(C13/B13) -> 0.98096633 | H13: =(C13-B13)/B13 -> -0.019033675 | I13: =(D13-B13) -> -129 | J13: =(D13/B13) -> 0.97639092 | K13: =(D13-B13)/B13 -> -0.023609078 | L13: =(E13-B13) -> 659 | M13: =(E13/B13) -> 1.1206076 | N13: =(E13-B13)/B13 -> 0.12060761 | O13: =IFERROR(__xludf.DUMMYFUNCTION("SPARKLINE({F13; I13; L13},{""charttype"",""line"";""color"",""green""}) "),"") | P13: =IFERROR(__xludf.DUMMYFUNCTION("SPARKLINE({G13; J13; M13},{""charttype"",""column"";""color"",""green""})"),"") | Q13: =IFERROR(__xludf.DUMMYFUNCTION("SPARKLINE({H13;K13;N13},{""charttype"",""line"";""color"",""black""})"),"")
A14: Нематериальные активы | B14: 2414 | C14: 3221 | D14: 7475 | E14: 21245 | F14: =(C14-B14) -> 807 | G14: =(C14/B14) -> 1.3342999 | H14: =(C14-B14)/B14 -> 0.33429992 | I14: =(D14-B14) -> 5061 | J14: =(D14/B14) -> 3.0965203 | K14: =(D14-B14)/B14 -> 2.0965203 | L14: =(E14-B14) -> 18831 | M14: =(E14/B14) -> 8.8007456 | N14: =(E14-B14)/B14 -> 7.8007456 | O14: =IFERROR(__xludf.DUMMYFUNCTION("SPARKLINE({F14; I14; L14},{""charttype"",""line"";""color"",""green""}) "),"") | P14: =IFERROR(__xludf.DUMMYFUNCTION("SPARKLINE({G14; J14; M14},{""charttype"",""column"";""color"",""green""})"),"") | Q14: =IFERROR(__xludf.DUMMYFUNCTION("SPARKLINE({H14;K14;N14},{""charttype"",""line"";""color"",""black""})"),"")
A15: Инвестиции в ассоциированные компании | B15: 419 | C15: 538 | D15: 518 | E15: 1541 | F15: =(C15-B15) -> 119 | G15: =(C15/B15) -> 1.2840095 | H15: =(C15-B15)/B15 -> 0.28400955 | I15: =(D15-B15) -> 99 | J15: =(D15/B15) -> 1.2362769 | K15: =(D15-B15)/B15 -> 0.23627685 | L15: =(E15-B15) -> 1122 | M15: =(E15/B15) -> 3.6778043 | N15: =(E15-B15)/B15 -> 2.6778043 | O15: =IFERROR(__xludf.DUMMYFUNCTION("SPARKLINE({F15; I15; L15},{""charttype"",""line"";""color"",""green""}) "),"") | P15: =IFERROR(__xludf.DUMMYFUNCTION("SPARKLINE({G15; J15; M15},{""charttype"",""column"";""color"",""green""})"),"") | Q15: =IFERROR(__xludf.DUMMYFUNCTION("SPARKLINE({H15;K15;N15},{""charttype"",""line"";""color"",""black""})"),"")
A16: Итого внеоборотные активы | B16: 831122 | C16: 919106 | D16: 863212 | E16: 903159 | F16: =(C16-B16) -> 87984 | G16: =(C16/B16) -> 1.1058617 | H16: =(C16-B16)/B16 -> 0.10586171 | I16: =(D16-B16) -> 32090 | J16: =(D16/B16) -> 1.0386105 | K16: =(D16-B16)/B16 -> 0.038610457 | L16: =(E16-B16) -> 72037 | M16: =(E16/B16) -> 1.0866744 | N16: =(E16-B16)/B16 -> 0.086674399 | O16: =IFERROR(__xludf.DUMMYFUNCTION("SPARKLINE({F16; I16; L16},{""charttype"",""line"";""color"",""green""}) "),"") | P16: =IFERROR(__xludf.DUMMYFUNCTION("SPARKLINE({G16; J16; M16},{""charttype"",""column"";""color"",""green""})"),"") | Q16: =IFERROR(__xludf.DUMMYFUNCTION("SPARKLINE({H16;K16;N16},{""charttype"",""line"";""color"",""black""})"),"")
A17: ИТОГО АКТИВЫ | B17: 1016204 | C17: 1109450 | D17: 1114014 | E17: 1156896 | F17: =(C17-B17) -> 93246 | G17: =(C17/B17) -> 1.0917591 | H17: =(C17-B17)/B17 -> 0.091759135 | I17: =(D17-B17) -> 97810 | J17: =(D17/B17) -> 1.0962504 | K17: =(D17-B17)/B17 -> 0.096250359 | L17: =(E17-B17) -> 140692 | M17: =(E17/B17) -> 1.1384486 | N17: =(E17-B17)/B17 -> 0.13844858 | O17: =IFERROR(__xludf.DUMMYFUNCTION("SPARKLINE({F17; I17; L17},{""charttype"",""line"";""color"",""green""}) "),"") | P17: =IFERROR(__xludf.DUMMYFUNCTION("SPARKLINE({G17; J17; M17},{""charttype"",""column"";""color"",""green""})"),"") | Q17: =IFERROR(__xludf.DUMMYFUNCTION("SPARKLINE({H17;K17;N17},{""charttype"",""line"";""color"",""black""})"),"")
A18: ОБЯЗАТЕЛЬСТВА И КАПИТАЛ
A19: Краткосрочные обязательства
A20: Краткосрочные кредиты и займы и краткосрочная часть долгосрочных кредитов и займов | B20: 34924 | C20: 17500 | D20: 44178 | E20: 19746 | F20: =(C20-B20) -> -17424 | G20: =(C20/B20) -> 0.50108808 | H20: =(C20-B20)/B20 -> -0.49891192 | I20: =(D20-B20) -> 9254 | J20: =(D20/B20) -> 1.2649754 | K20: =(D20-B20)/B20 -> 0.26497538 | L20: =(E20-B20) -> -15178 | M20: =(E20/B20) -> 0.56539915 | N20: =(E20-B20)/B20 -> -0.43460085 | O20: =IFERROR(__xludf.DUMMYFUNCTION("SPARKLINE({F20; I20; L20},{""charttype"",""line"";""color"",""green""}) "),"") | P20: =IFERROR(__xludf.DUMMYFUNCTION("SPARKLINE({G20; J20; M20},{""charttype"",""column"";""color"",""green""})"),"") | Q20: =IFERROR(__xludf.DUMMYFUNCTION("SPARKLINE({H20;K20;N20},{""charttype"",""line"";""color"",""black""})"),"")
A21: Обязательства по текущему налогу на прибыль | B21: 4 | C21: 141 | D21: 905 | E21: 754 | F21: =(C21-B21) -> 137 | G21: =(C21/B21) -> 35.25 | H21: =(C21-B21)/B21 -> 34.25 | I21: =(D21-B21) -> 901 | J21: =(D21/B21) -> 226.25 | K21: =(D21-B21)/B21 -> 225.25 | L21: =(E21-B21) -> 750 | M21: =(E21/B21) -> 188.5 | N21: =(E21-B21)/B21 -> 187.5 | O21: =IFERROR(__xludf.DUMMYFUNCTION("SPARKLINE({F21; I21; L21},{""charttype"",""line"";""color"",""green""}) "),"") | P21: =IFERROR(__xludf.DUMMYFUNCTION("SPARKLINE({G21; J21; M21},{""charttype"",""column"";""color"",""green""})"),"") | Q21: =IFERROR(__xludf.DUMMYFUNCTION("SPARKLINE({H21;K21;N21},{""charttype"",""line"";""color"",""black""})"),"")
A22: Итого краткосрочные обязательства | B22: 281285 | C22: 272588 | D22: 339604 | E22: 409065 | F22: =(C22-B22) -> -8697 | G22: =(C22/B22) -> 0.96908118 | H22: =(C22-B22)/B22 -> -0.030918819 | I22: =(D22-B22) -> 58319 | J22: =(D22/B22) -> 1.2073306 | K22: =(D22-B22)/B22 -> 0.20733064 | L22: =(E22-B22) -> 127780 | M22: =(E22/B22) -> 1.4542724 | N22: =(E22-B22)/B22 -> 0.45427236 | O22: =IFERROR(__xludf.DUMMYFUNCTION("SPARKLINE({F22; I22; L22},{""charttype"",""line"";""color"",""green""}) "),"") | P22: =IFERROR(__xludf.DUMMYFUNCTION("SPARKLINE({G22; J22; M22},{""charttype"",""column"";""color"",""green""})"),"") | Q22: =IFERROR(__xludf.DUMMYFUNCTION("SPARKLINE({H22;K22;N22},{""charttype"",""line"";""color"",""black""})"),"")
A23: Долгосрочные обязательства
A24: Долгосрочные кредиты и займы | B24: 53711 | C24: 114768 | D24: 60190 | E24: 40722 | F24: =(C24-B24) -> 61057 | G24: =(C24/B24) -> 2.136769 | H24: =(C24-B24)/B24 -> 1.136769 | I24: =(D24-B24) -> 6479 | J24: =(D24/B24) -> 1.1206271 | K24: =(D24-B24)/B24 -> 0.12062706 | L24: =(E24-B24) -> -12989 | M24: =(E24/B24) -> 0.75816872 | N24: =(E24-B24)/B24 -> -0.24183128 | O24: =IFERROR(__xludf.DUMMYFUNCTION("SPARKLINE({F24; I24; L24},{""charttype"",""line"";""color"",""green""}) "),"") | P24: =IFERROR(__xludf.DUMMYFUNCTION("SPARKLINE({G24; J24; M24},{""charttype"",""column"";""color"",""green""})"),"") | Q24: =IFERROR(__xludf.DUMMYFUNCTION("SPARKLINE({H24;K24;N24},{""charttype"",""line"";""color"",""black""})"),"")
A25: Прочие долгосрочные обязательства | B25: 20666 | C25: 15552 | D25: 9913 | E25: 4982 | F25: =(C25-B25) -> -5114 | G25: =(C25/B25) -> 0.7525404 | H25: =(C25-B25)/B25 -> -0.2474596 | I25: =(D25-B25) -> -10753 | J25: =(D25/B25) -> 0.47967676 | K25: =(D25-B25)/B25 -> -0.52032324 | L25: =(E25-B25) -> -15684 | M25: =(E25/B25) -> 0.24107229 | N25: =(E25-B25)/B25 -> -0.75892771 | O25: =IFERROR(__xludf.DUMMYFUNCTION("SPARKLINE({F25; I25; L25},{""charttype"",""line"";""color"",""green""}) "),"") | P25: =IFERROR(__xludf.DUMMYFUNCTION("SPARKLINE({G25; J25; M25},{""charttype"",""column"";""color"",""green""})"),"") | Q25: =IFERROR(__xludf.DUMMYFUNCTION("SPARKLINE({H25;K25;N25},{""charttype"",""line"";""color"",""black""})"),"") | U25: Темпы роста капитала Аэрофлота относительно базового года
A26: Итого долгосрочные обязательства | B26: 850265 | C26: 983300 | D26: 873164 | E26: 820328 | F26: =(C26-B26) -> 133035 | G26: =(C26/B26) -> 1.156463 | H26: =(C26-B26)/B26 -> 0.15646299 | I26: =(D26-B26) -> 22899 | J26: =(D26/B26) -> 1.0269316 | K26: =(D26-B26)/B26 -> 0.026931604 | L26: =(E26-B26) -> -29937 | M26: =(E26/B26) -> 0.96479098 | N26: =(E26-B26)/B26 -> -0.035209023 | O26: =IFERROR(__xludf.DUMMYFUNCTION("SPARKLINE({F26; I26; L26},{""charttype"",""line"";""color"",""green""}) "),"") | P26: =IFERROR(__xludf.DUMMYFUNCTION("SPARKLINE({G26; J26; M26},{""charttype"",""column"";""color"",""green""})"),"") | Q26: =IFERROR(__xludf.DUMMYFUNCTION("SPARKLINE({H26;K26;N26},{""charttype"",""line"";""color"",""black""})"),"") | U26: год | V26: Уставный капитал | W26: Добавочный капитал | X26: Капитал, приходящийся на акционеров компании | Y26: Держатели неконтролирующих долей участия
A27: ИТОГО ОБЯЗАТЕЛЬСТВА | B27: 1131550 | C27: 1255888 | D27: 1212768 | E27: 1229393 | F27: =(C27-B27) -> 124338 | G27: =(C27/B27) -> 1.1098829 | H27: =(C27-B27)/B27 -> 0.1098829 | I27: =(D27-B27) -> 81218 | J27: =(D27/B27) -> 1.0717759 | K27: =(D27-B27)/B27 -> 0.071775883 | L27: =(E27-B27) -> 97843 | M27: =(E27/B27) -> 1.0864681 | N27: =(E27-B27)/B27 -> 0.086468119 | O27: =IFERROR(__xludf.DUMMYFUNCTION("SPARKLINE({F27; I27; L27},{""charttype"",""line"";""color"",""green""}) "),"") | P27: =IFERROR(__xludf.DUMMYFUNCTION("SPARKLINE({G27; J27; M27},{""charttype"",""column"";""color"",""green""})"),"") | Q27: =IFERROR(__xludf.DUMMYFUNCTION("SPARKLINE({H27;K27;N27},{""charttype"",""line"";""color"",""black""})"),"") | U27: 2021г | V27: =(C29/B29) -> 1 | W27: =(C30/B30) -> 1 | X27: =(C31/B31) -> 1.285082 | Y27: =(C32/B32) -> 1.0484808
A28: Капитал | U28: 2023г | V28: =(D29/B29) -> 1.568511 | W28: =(D30/B30) -> 1.8348179 | X28: =(D31/B31) -> 0.79371103 | Y28: =(D32/B32) -> 1.7451783
A29: Уставный капитал | B29: 2693 | C29: 2693 | D29: 4224 | E29: 4224 | F29: =(C29-B29) -> 0 | G29: =(C29/B29) -> 1 | H29: =(C29-B29)/B29 -> 0 | I29: =(D29-B29) -> 1531 | J29: =(D29/B29) -> 1.568511 | K29: =(D29-B29)/B29 -> 0.56851095 | L29: =(E29-B29) -> 1531 | M29: =(E29/B29) -> 1.568511 | N29: =(E29-B29)/B29 -> 0.56851095 | O29: =IFERROR(__xludf.DUMMYFUNCTION("SPARKLINE({F29; I29; L29},{""charttype"",""line"";""color"",""green""}) "),"") | P29: =IFERROR(__xludf.DUMMYFUNCTION("SPARKLINE({G29; J29; M29},{""charttype"",""column"";""color"",""green""})"),"") | Q29: =IFERROR(__xludf.DUMMYFUNCTION("SPARKLINE({H29;K29;N29},{""charttype"",""line"";""color"",""black""})"),"") | U29: 2024г | V29: =(E29/B29) -> 1.568511 | W29: =(E30/B30) -> 1.823128 | X29: =(E31/B31) -> 0.51692399 | Y29: =(E32/B32) -> 2.2173052
A30: Добавочный капитал | B30: 78701 | C30: 78701 | D30: 144402 | E30: 143482 | F30: =(C30-B30) -> 0 | G30: =(C30/B30) -> 1 | H30: =(C30-B30)/B30 -> 0 | I30: =(D30-B30) -> 65701 | J30: =(D30/B30) -> 1.8348179 | K30: =(D30-B30)/B30 -> 0.83481785 | L30: =(E30-B30) -> 64781 | M30: =(E30/B30) -> 1.823128 | N30: =(E30-B30)/B30 -> 0.82312804 | O30: =IFERROR(__xludf.DUMMYFUNCTION("SPARKLINE({F30; I30; L30},{""charttype"",""line"";""color"",""green""}) "),"") | P30: =IFERROR(__xludf.DUMMYFUNCTION("SPARKLINE({G30; J30; M30},{""charttype"",""column"";""color"",""green""})"),"") | Q30: =IFERROR(__xludf.DUMMYFUNCTION("SPARKLINE({H30;K30;N30},{""charttype"",""line"";""color"",""black""})"),"")
A31: Капитал, приходящийся на акционеров Компании | B31: -107776 | C31: -138501 | D31: -85543 | E31: -55712 | F31: =(C31-B31) -> -30725 | G31: =(C31/B31) -> 1.285082 | H31: =(C31-B31)/B31 -> 0.28508202 | I31: =(D31-B31) -> 22233 | J31: =(D31/B31) -> 0.79371103 | K31: =(D31-B31)/B31 -> -0.20628897 | L31: =(E31-B31) -> 52064 | M31: =(E31/B31) -> 0.51692399 | N31: =(E31-B31)/B31 -> -0.48307601 | O31: =IFERROR(__xludf.DUMMYFUNCTION("SPARKLINE({F31; I31; L31},{""charttype"",""line"";""color"",""green""}) "),"") | P31: =IFERROR(__xludf.DUMMYFUNCTION("SPARKLINE({G31; J31; M31},{""charttype"",""column"";""color"",""green""})"),"") | Q31: =IFERROR(__xludf.DUMMYFUNCTION("SPARKLINE({H31;K31;N31},{""charttype"",""line"";""color"",""black""})"),"")
A32: Держатели неконтролирующих долей участия | B32: -7570 | C32: -7937 | D32: -13211 | E32: -16785 | F32: =(C32-B32) -> -367 | G32: =(C32/B32) -> 1.0484808 | H32: =(C32-B32)/B32 -> 0.048480845 | I32: =(D32-B32) -> -5641 | J32: =(D32/B32) -> 1.7451783 | K32: =(D32-B32)/B32 -> 0.74517834 | L32: =(E32-B32) -> -9215 | M32: =(E32/B32) -> 2.2173052 | N32: =(E32-B32)/B32 -> 1.2173052 | O32: =IFERROR(__xludf.DUMMYFUNCTION("SPARKLINE({F32; I32; L32},{""charttype"",""line"";""color"",""green""}) "),"") | P32: =IFERROR(__xludf.DUMMYFUNCTION("SPARKLINE({G32; J32; M32},{""charttype"",""column"";""color"",""green""})"),"") | Q32: =IFERROR(__xludf.DUMMYFUNCTION("SPARKLINE({H32;K32;N32},{""charttype"",""line"";""color"",""black""})"),"")
A33: ИТОГО КАПИТАЛ | B33: -115346 | C33: -146438 | D33: -98754 | E33: -72497 | F33: =(C33-B33) -> -31092 | G33: =(C33/B33) -> 1.2695542 | H33: =(C33-B33)/B33 -> 0.26955421 | I33: =(D33-B33) -> 16592 | J33: =(D33/B33) -> 0.85615453 | K33: =(D33-B33)/B33 -> -0.14384547 | L33: =(E33-B33) -> 42849 | M33: =(E33/B33) -> 0.62851768 | N33: =(E33-B33)/B33 -> -0.37148232 | O33: =IFERROR(__xludf.DUMMYFUNCTION("SPARKLINE({F33; I33; L33},{""charttype"",""line"";""color"",""green""}) "),"") | P33: =IFERROR(__xludf.DUMMYFUNCTION("SPARKLINE({G33; J33; M33},{""charttype"",""column"";""color"",""green""})"),"") | Q33: =IFERROR(__xludf.DUMMYFUNCTION("SPARKLINE({H33;K33;N33},{""charttype"",""line"";""color"",""black""})"),"")
A34: ИТОГО ОБЯЗАТЕЛЬСТВА И КАПИТАЛ | B34: 1016204 | C34: 1109450 | D34: 1114014 | E34: 1156896 | F34: =(C34-B34) -> 93246 | G34: =(C34/B34) -> 1.0917591 | H34: =(C34-B34)/B34 -> 0.091759135 | I34: =(D34-B34) -> 97810 | J34: =(D34/B34) -> 1.0962504 | K34: =(D34-B34)/B34 -> 0.096250359 | L34: =(E34-B34) -> 140692 | M34: =(E34/B34) -> 1.1384486 | N34: =(E34-B34)/B34 -> 0.13844858 | O34: =IFERROR(__xludf.DUMMYFUNCTION("SPARKLINE({F34; I34; L34},{""charttype"",""line"";""color"",""green""}) "),"") | P34: =IFERROR(__xludf.DUMMYFUNCTION("SPARKLINE({G34; J34; M34},{""charttype"",""column"";""color"",""green""})"),"") | Q34: =IFERROR(__xludf.DUMMYFUNCTION("SPARKLINE({H34;K34;N34},{""charttype"",""line"";""color"",""black""})"),"")
A37: Горизонтальный анализ (Ютэир) ОФП | F37: Изменения (базовый год 2020)
F38: Абсолютные отклонения | G38: Относительные отклонения | I38: Абсолютные отклонения | J38: Относительные отклонения | L38: Абсолютные отклонения | M38: Относительные отклонения
A39: на 31 декабря 202X года в миллионах рублей, если не указано иное | G39: Темп роста | H39: Темп прироста | J39: Темп роста | K39: Темп прироста | M39: Темп роста | N39: Темп прироста
B40: 2020 г. | C40: 2021 г. | D40: 2023 г. | E40: 2024г. | F40: 2021 г. | I40: 2023 г. | L40: 2024 г.
A41: АКТИВЫ
A42: Внеоборотные активы
A43: Активы в форме права пользования | B43: 33577 | C43: 36306 | D43: 24210 | E43: 25161 | F43: =(C43-B43) -> 2729 | G43: =(C43/B43) -> 1.0812759 | H43: =(C43-B43)/B43 -> 0.081275873 | I43: =(D43-B43) -> -9367 | J43: =(D43/B43) -> 0.72102928 | K43: =(D43-B43)/B43 -> -0.27897072 | L43: =(E43-B43) -> -8416 | M43: =(E43/B43) -> 0.74935224 | N43: =(E43-B43)/B43 -> -0.25064776
A44: Основные средства | B44: 26627 | C44: 30187 | D44: 58662 | E44: 62334 | F44: =(C44-B44) -> 3560 | G44: =(C44/B44) -> 1.1336989 | H44: =(C44-B44)/B44 -> 0.13369888 | I44: =(D44-B44) -> 32035 | J44: =(D44/B44) -> 2.2031021 | K44: =(D44-B44)/B44 -> 1.2031021 | L44: =(E44-B44) -> 35707 | M44: =(E44/B44) -> 2.3410072 | N44: =(E44-B44)/B44 -> 1.3410072
A45: Долгосрочные финансовые активы | B45: 160 | C45: 2755 | D45: 8562 | E45: 9874 | F45: =(C45-B45) -> 2595 | G45: =(C45/B45) -> 17.21875 | H45: =(C45-B45)/B45 -> 16.21875 | I45: =(D45-B45) -> 8402 | J45: =(D45/B45) -> 53.5125 | K45: =(D45-B45)/B45 -> 52.5125 | L45: =(E45-B45) -> 9714 | M45: =(E45/B45) -> 61.7125 | N45: =(E45-B45)/B45 -> 60.7125
A46: Нематериальные активы | B46: 56 | C46: 83 | D46: 40 | E46: 35 | F46: =(C46-B46) -> 27 | G46: =(C46/B46) -> 1.4821429 | H46: =(C46-B46)/B46 -> 0.48214286 | I46: =(D46-B46) -> -16 | J46: =(D46/B46) -> 0.71428571 | K46: =(D46-B46)/B46 -> -0.28571429 | L46: =(E46-B46) -> -21 | M46: =(E46/B46) -> 0.625 | N46: =(E46-B46)/B46 -> -0.375
A47: Инвестиции в компании, учитываемые методом долевого участия | B47: 486 | C47: 404 | D47: 792 | E47: 82 | F47: =(C47-B47) -> -82 | G47: =(C47/B47) -> 0.83127572 | H47: =(C47-B47)/B47 -> -0.16872428 | I47: =(D47-B47) -> 306 | J47: =(D47/B47) -> 1.6296296 | K47: =(D47-B47)/B47 -> 0.62962963 | L47: =(E47-B47) -> -404 | M47: =(E47/B47) -> 0.16872428 | N47: =(E47-B47)/B47 -> -0.83127572
A48: Итого внеоборотные активы | B48: 63350 | C48: 71618 | D48: 95156 | E48: 99834 | F48: =(C48-B48) -> 8268 | G48: =(C48/B48) -> 1.130513 | H48: =(C48-B48)/B48 -> 0.13051302 | I48: =(D48-B48) -> 31806 | J48: =(D48/B48) -> 1.5020679 | K48: =(D48-B48)/B48 -> 0.50206788 | L48: =(E48-B48) -> 36484 | M48: =(E48/B48) -> 1.5759116 | N48: =(E48-B48)/B48 -> 0.5759116
A49: Оборотные активы
A50: Денежные средства и их эквиваленты | B50: 12679 | C50: 7569 | D50: 5537 | E50: 5337 | F50: =(C50-B50) -> -5110 | G50: =(C50/B50) -> 0.59697137 | H50: =(C50-B50)/B50 -> -0.40302863 | I50: =(D50-B50) -> -7142 | J50: =(D50/B50) -> 0.43670636 | K50: =(D50-B50)/B50 -> -0.56329364 | L50: =(E50-B50) -> -7342 | M50: =(E50/B50) -> 0.42093225 | N50: =(E50-B50)/B50 -> -0.57906775
A51: Торговая и прочая дебиторская задолженность | B51: 3675 | C51: 5498 | D51: 6694 | E51: 6956 | F51: =(C51-B51) -> 1823 | G51: =(C51/B51) -> 1.4960544 | H51: =(C51-B51)/B51 -> 0.49605442 | I51: =(D51-B51) -> 3019 | J51: =(D51/B51) -> 1.8214966 | K51: =(D51-B51)/B51 -> 0.8214966 | L51: =(E51-B51) -> 3281 | M51: =(E51/B51) -> 1.8927891 | N51: =(E51-B51)/B51 -> 0.89278912
A52: Итого оборотные активы | B52: 22756 | C52: 23840 | D52: 28007 | E52: 30191 | F52: =(C52-B52) -> 1084 | G52: =(C52/B52) -> 1.0476358 | H52: =(C52-B52)/B52 -> 0.047635788 | I52: =(D52-B52) -> 5251 | J52: =(D52/B52) -> 1.2307523 | K52: =(D52-B52)/B52 -> 0.23075233 | L52: =(E52-B52) -> 7435 | M52: =(E52/B52) -> 1.326727 | N52: =(E52-B52)/B52 -> 0.32672702
A53: Всего активы | B53: 86106 | C53: 95458 | D53: 123163 | E53: 130350 | F53: =(C53-B53) -> 9352 | G53: =(C53/B53) -> 1.1086103 | H53: =(C53-B53)/B53 -> 0.10861032 | I53: =(D53-B53) -> 37057 | J53: =(D53/B53) -> 1.4303649 | K53: =(D53-B53)/B53 -> 0.4303649 | L53: =(E53-B53) -> 44244 | M53: =(E53/B53) -> 1.5138318 | N53: =(E53-B53)/B53 -> 0.51383179
A54: Собственный капитал
A55: Акционерный капитал | B55: 3702 | C55: 7896 | D55: 7896 | E55: 7896 | F55: =(C55-B55) -> 4194 | G55: =(C55/B55) -> 2.1329011 | H55: =(C55-B55)/B55 -> 1.1329011 | I55: =(D55-B55) -> 4194 | J55: =(D55/B55) -> 2.1329011 | K55: =(D55-B55)/B55 -> 1.1329011 | L55: =(E55-B55) -> 4194 | M55: =(E55/B55) -> 2.1329011 | N55: =(E55-B55)/B55 -> 1.1329011
A56: Эмиссионный доход | B56: 21875 | C56: 31311 | D56: 31311 | E56: 31311 | F56: =(C56-B56) -> 9436 | G56: =(C56/B56) -> 1.43136 | H56: =(C56-B56)/B56 -> 0.43136 | I56: =(D56-B56) -> 9436 | J56: =(D56/B56) -> 1.43136 | K56: =(D56-B56)/B56 -> 0.43136 | L56: =(E56-B56) -> 9436 | M56: =(E56/B56) -> 1.43136 | N56: =(E56-B56)/B56 -> 0.43136
A57: Итого собственный капитал, принадлежащий акционерам Компании | B57: -25602 | C57: 10154 | D57: 22353 | E57: 13851 | F57: =(C57-B57) -> 35756 | G57: =(C57/B57) -> -0.39660964 | H57: =(C57-B57)/B57 -> -1.3966096 | I57: =(D57-B57) -> 47955 | J57: =(D57/B57) -> -0.87309585 | K57: =(D57-B57)/B57 -> -1.8730959 | L57: =(E57-B57) -> 39453 | M57: =(E57/B57) -> -0.54101242 | N57: =(E57-B57)/B57 -> -1.5410124
A58: Итого собственный капитал | B58: -4925 | C58: 10801 | D58: 23067 | E58: 14445 | F58: =(C58-B58) -> 15726 | G58: =(C58/B58) -> -2.1930964 | H58: =(C58-B58)/B58 -> -3.1930964 | I58: =(D58-B58) -> 27992 | J58: =(D58/B58) -> -4.6836548 | K58: =(D58-B58)/B58 -> -5.6836548 | L58: =(E58-B58) -> 19370 | M58: =(E58/B58) -> -2.9329949 | N58: =(E58-B58)/B58 -> -3.9329949
A59: Долгосрочные обязательства
A60: Кредиты и займы | B60: 12714 | C60: 19563 | D60: 27881 | E60: 26716 | F60: =(C60-B60) -> 6849 | G60: =(C60/B60) -> 1.5386975 | H60: =(C60-B60)/B60 -> 0.5386975 | I60: =(D60-B60) -> 15167 | J60: =(D60/B60) -> 2.1929369 | K60: =(D60-B60)/B60 -> 1.1929369 | L60: =(E60-B60) -> 14002 | M60: =(E60/B60) -> 2.1013056 | N60: =(E60-B60)/B60 -> 1.1013056
A61: Итого долгосрочные обязательства | B61: 36742 | C61: 57531 | D61: 63353 | E61: 67681 | F61: =(C61-B61) -> 20789 | G61: =(C61/B61) -> 1.5658102 | H61: =(C61-B61)/B61 -> 0.56581024 | I61: =(D61-B61) -> 26611 | J61: =(D61/B61) -> 1.7242665 | K61: =(D61-B61)/B61 -> 0.72426651 | L61: =(E61-B61) -> 30939 | M61: =(E61/B61) -> 1.8420609 | N61: =(E61-B61)/B61 -> 0.84206086
A62: Краткосрочные обязательства
A63: Кредиты и займы | B63: 48782 | C63: 5589 | D63: 2863 | E63: 4393 | F63: =(C63-B63) -> -43193 | G63: =(C63/B63) -> 0.11457095 | H63: =(C63-B63)/B63 -> -0.88542905 | I63: =(D63-B63) -> -45919 | J63: =(D63/B63) -> 0.058689681 | K63: =(D63-B63)/B63 -> -0.94131032 | L63: =(E63-B63) -> -44389 | M63: =(E63/B63) -> 0.090053708 | N63: =(E63-B63)/B63 -> -0.90994629
A64: Кредиторская задолженность по налогу на прибыль | B64: 63 | C64: 5298 | D64: 111 | E64: 18 | F64: =(C64-B64) -> 5235 | G64: =(C64/B64) -> 84.095238 | H64: =(C64-B64)/B64 -> 83.095238 | I64: =(D64-B64) -> 48 | J64: =(D64/B64) -> 1.7619048 | K64: =(D64-B64)/B64 -> 0.76190476 | L64: =(E64-B64) -> -45 | M64: =(E64/B64) -> 0.28571429 | N64: =(E64-B64)/B64 -> -0.71428571
A65: Итого краткосрочные обязательства | B65: 74290 | C65: 27125 | D65: 36743 | E65: 48223 | F65: =(C65-B65) -> -47165 | G65: =(C65/B65) -> 0.36512317 | H65: =(C65-B65)/B65 -> -0.63487683 | I65: =(D65-B65) -> -37547 | J65: =(D65/B65) -> 0.49458877 | K65: =(D65-B65)/B65 -> -0.50541123 | L65: =(E65-B65) -> -26067 | M65: =(E65/B65) -> 0.64911832 | N65: =(E65-B65)/B65 -> -0.35088168
A66: Итого обязательства | B66: 111032 | C66: 84657 | D66: 100096 | E66: 115905 | F66: =(C66-B66) -> -26375 | G66: =(C66/B66) -> 0.76245587 | H66: =(C66-B66)/B66 -> -0.23754413 | I66: =(D66-B66) -> -10936 | J66: =(D66/B66) -> 0.90150587 | K66: =(D66-B66)/B66 -> -0.098494128 | L66: =(E66-B66) -> 4873 | M66: =(E66/B66) -> 1.0438882 | N66: =(E66-B66)/B66 -> 0.043888248
A67: Итого собственный капитал и обязательства | B67: 86106 | C67: 95458 | D67: 123163 | E67: 130350 | F67: =(C67-B67) -> 9352 | G67: =(C67/B67) -> 1.1086103 | H67: =(C67-B67)/B67 -> 0.10861032 | I67: =(D67-B67) -> 37057 | J67: =(D67/B67) -> 1.4303649 | K67: =(D67-B67)/B67 -> 0.4303649 | L67: =(E67-B67) -> 44244 | M67: =(E67/B67) -> 1.5138318 | N67: =(E67-B67)/B67 -> 0.51383179
A70: Горизонтальный анализ (TurkishAirlines) ОФП | F70: Изменения (базовый год 2020)
F71: Абсолютные отклонения | G71: Относительные отклонения | I71: Абсолютные отклонения | J71: Относительные отклонения | L71: Абсолютные отклонения | M71: Относительные отклонения
A72: на 31 декабря 202X года в миллионах рублей, если не указано иное | G72: Темп роста | H72: Темп прироста | J72: Темп роста | K72: Темп прироста | M72: Темп роста | N72: Темп прироста
B73: 2020 г. | C73: 2021 г. | D73: 2023 г. | E73: 2024 г. | F73: 2021 г. | I73: 2023 г. | L73: 2024 г.
A74: АКТИВЫ
A75: ВНЕОБОРОТНЫЕ АКТИВЫ
A76: Активы в форме права пользования | B76: 1093498 | C76: 1118140 | D76: 1540448 | E76: 1797750 | F76: =(C76-B76) -> 24642 | G76: =(C76/B76) -> 1.022535 | H76: =(C76-B76)/B76 -> 0.022535021 | I76: =(D76-B76) -> 446950 | J76: =(D76/B76) -> 1.4087342 | K76: =(D76-B76)/B76 -> 0.40873417 | L76: =(E76-B76) -> 704252 | M76: =(E76/B76) -> 1.6440359 | N76: =(E76-B76)/B76 -> 0.64403593
A77: Основные средства | B77: 306730 | C77: 322936 | D77: 552825 | E77: 719610 | F77: =(C77-B77) -> 16206 | G77: =(C77/B77) -> 1.0528347 | H77: =(C77-B77)/B77 -> 0.052834741 | I77: =(D77-B77) -> 246095 | J77: =(D77/B77) -> 1.802318 | K77: =(D77-B77)/B77 -> 0.802318 | L77: =(E77-B77) -> 412880 | M77: =(E77/B77) -> 2.3460698 | N77: =(E77-B77)/B77 -> 1.3460698
A78: Финансовые вложения | B78: 5550 | C78: 6512 | D78: 36218 | E78: 113526 | F78: =(C78-B78) -> 962 | G78: =(C78/B78) -> 1.1733333 | H78: =(C78-B78)/B78 -> 0.17333333 | I78: =(D78-B78) -> 30668 | J78: =(D78/B78) -> 6.5257658 | K78: =(D78-B78)/B78 -> 5.5257658 | L78: =(E78-B78) -> 107976 | M78: =(E78/B78) -> 20.455135 | N78: =(E78-B78)/B78 -> 19.455135
A79: Нематериальные активы
A80: Прочие нематериальные активы | B80: 6586 | C80: 6068 | D80: 7917 | E80: 11424 | F80: =(C80-B80) -> -518 | G80: =(C80/B80) -> 0.92134831 | H80: =(C80-B80)/B80 -> -0.078651685 | I80: =(D80-B80) -> 1331 | J80: =(D80/B80) -> 1.2020954 | K80: =(D80-B80)/B80 -> 0.20209535 | L80: =(E80-B80) -> 4838 | M80: =(E80/B80) -> 1.7345885 | N80: =(E80-B80)/B80 -> 0.73458852
A81: Гудвил | B81: 888 | C81: 888 | D81: 2457 | E81: 2754 | F81: =(C81-B81) -> 0 | G81: =(C81/B81) -> 1 | H81: =(C81-B81)/B81 -> 0 | I81: =(D81-B81) -> 1569 | J81: =(D81/B81) -> 2.7668919 | K81: =(D81-B81)/B81 -> 1.7668919 | L81: =(E81-B81) -> 1866 | M81: =(E81/B81) -> 3.1013514 | N81: =(E81-B81)/B81 -> 2.1013514
A82: Инвестиции, учитываемые методом долевого участия | B82: 18944 | C82: 17538 | D82: 45227 | E82: 65688 | F82: =(C82-B82) -> -1406 | G82: =(C82/B82) -> 0.92578125 | H82: =(C82-B82)/B82 -> -0.07421875 | I82: =(D82-B82) -> 26283 | J82: =(D82/B82) -> 2.387405 | K82: =(D82-B82)/B82 -> 1.387405 | L82: =(E82-B82) -> 46744 | M82: =(E82/B82) -> 3.4674831 | N82: =(E82-B82)/B82 -> 2.4674831
A83: ИТОГО ВНЕОБОРОТНЫЕ АКТИВЫ | B83: 1580048 | C83: 1598326 | D83: 2463916 | E83: 3058062 | F83: =(C83-B83) -> 18278 | G83: =(C83/B83) -> 1.011568 | H83: =(C83-B83)/B83 -> 0.011568003 | I83: =(D83-B83) -> 883868 | J83: =(D83/B83) -> 1.5593931 | K83: =(D83-B83)/B83 -> 0.55939313 | L83: =(E83-B83) -> 1478014 | M83: =(E83/B83) -> 1.9354235 | N83: =(E83-B83)/B83 -> 0.93542348
A84: ОБОРОТНЫЕ АКТИВЫ
A85: Денежные средства и денежные эквиваленты | B85: 134014 | C85: 198098 | D85: 62153 | E85: 277542 | F85: =(C85-B85) -> 64084 | G85: =(C85/B85) -> 1.4781888 | H85: =(C85-B85)/B85 -> 0.47818885 | I85: =(D85-B85) -> -71861 | J85: =(D85/B85) -> 0.4637799 | K85: =(D85-B85)/B85 -> -0.5362201 | L85: =(E85-B85) -> 143528 | M85: =(E85/B85) -> 2.0709926 | N85: =(E85-B85)/B85 -> 1.0709926
A86: Дебиторская задолженность
A87: Аффилированные лица | B87: 1332 | C87: 1776 | D87: 4550 | E87: 4386 | F87: =(C87-B87) -> 444 | G87: =(C87/B87) -> 1.3333333 | H87: =(C87-B87)/B87 -> 0.33333333 | I87: =(D87-B87) -> 3218 | J87: =(D87/B87) -> 3.4159159 | K87: =(D87-B87)/B87 -> 2.4159159 | L87: =(E87-B87) -> 3054 | M87: =(E87/B87) -> 3.2927928 | N87: =(E87-B87)/B87 -> 2.2927928
A88: Третьи стороны | B88: 45806 | C88: 66674 | D88: 73346 | E88: 87924 | F88: =(C88-B88) -> 20868 | G88: =(C88/B88) -> 1.4555735 | H88: =(C88-B88)/B88 -> 0.45557351 | I88: =(D88-B88) -> 27540 | J88: =(D88/B88) -> 1.6012313 | K88: =(D88-B88)/B88 -> 0.60123128 | L88: =(E88-B88) -> 42118 | M88: =(E88/B88) -> 1.9194865 | N88: =(E88-B88)/B88 -> 0.91948653
A89: Прочая дебиторская задолженность
A90: Аффилированные лица | B90: 444 | C90: 444 | D90: 819 | E90: 918 | F90: =(C90-B90) -> 0 | G90: =(C90/B90) -> 1 | H90: =(C90-B90)/B90 -> 0 | I90: =(D90-B90) -> 375 | J90: =(D90/B90) -> 1.8445946 | K90: =(D90-B90)/B90 -> 0.84459459 | L90: =(E90-B90) -> 474 | M90: =(E90/B90) -> 2.0675676 | N90: =(E90-B90)/B90 -> 1.0675676
A91: Третьи стороны | B91: 81030 | C91: 58534 | D91: 80080 | E91: 138618 | F91: =(C91-B91) -> -22496 | G91: =(C91/B91) -> 0.72237443 | H91: =(C91-B91)/B91 -> -0.27762557 | I91: =(D91-B91) -> -950 | J91: =(D91/B91) -> 0.98827595 | K91: =(D91-B91)/B91 -> -0.011724053 | L91: =(E91-B91) -> 57588 | M91: =(E91/B91) -> 1.7106997 | N91: =(E91-B91)/B91 -> 0.71069974
A92: ИТОГО ОБОРОТНЫЕ АКТИВЫ | B92: 309172 | C92: 365412 | D92: 782145 | E92: 988686 | F92: =(C92-B92) -> 56240 | G92: =(C92/B92) -> 1.1819052 | H92: =(C92-B92)/B92 -> 0.18190522 | I92: =(D92-B92) -> 472973 | J92: =(D92/B92) -> 2.5298054 | K92: =(D92-B92)/B92 -> 1.5298054 | L92: =(E92-B92) -> 679514 | M92: =(E92/B92) -> 3.197851 | N92: =(E92-B92)/B92 -> 2.197851
A93: ИТОГО АКТИВЫ | B93: 1889220 | C93: 1963738 | D93: 3246061 | E93: 4046748 | F93: =(C93-B93) -> 74518 | G93: =(C93/B93) -> 1.0394438 | H93: =(C93-B93)/B93 -> 0.039443792 | I93: =(D93-B93) -> 1356841 | J93: =(D93/B93) -> 1.7182017 | K93: =(D93-B93)/B93 -> 0.71820169 | L93: =(E93-B93) -> 2157528 | M93: =(E93/B93) -> 2.1420205 | N93: =(E93-B93)/B93 -> 1.1420205
A94: ОБЯЗАТЕЛЬСТВА И КАПИТАЛ
A95: КАПИТАЛ
A96: Уставный капитал | B96: 118178 | C96: 118178 | D96: 145327 | E96: 162894 | F96: =(C96-B96) -> 0 | G96: =(C96/B96) -> 1 | H96: =(C96-B96)/B96 -> 0 | I96: =(D96-B96) -> 27149 | J96: =(D96/B96) -> 1.2297297 | K96: =(D96-B96)/B96 -> 0.22972973 | L96: =(E96-B96) -> 44716 | M96: =(E96/B96) -> 1.3783784 | N96: =(E96-B96)/B96 -> 0.37837838
A97: ИТОГО КАПИТАЛ | B97: 398342 | C97: 505938 | D97: 1416233 | E97: 1970028 | F97: =(C97-B97) -> 107596 | G97: =(C97/B97) -> 1.2701096 | H97: =(C97-B97)/B97 -> 0.2701096 | I97: =(D97-B97) -> 1017891 | J97: =(D97/B97) -> 3.5553193 | K97: =(D97-B97)/B97 -> 2.5553193 | L97: =(E97-B97) -> 1571686 | M97: =(E97/B97) -> 4.9455694 | N97: =(E97-B97)/B97 -> 3.9455694
A98: ДОЛГОСРОЧНЫЕ ОБЯЗАТЕЛЬСТВА
A99: Долгосрочные займы | B99: 198394 | C99: 172642 | D99: 42952 | E99: 3366 | F99: =(C99-B99) -> -25752 | G99: =(C99/B99) -> 0.87019769 | H99: =(C99-B99)/B99 -> -0.12980231 | I99: =(D99-B99) -> -155442 | J99: =(D99/B99) -> 0.21649848 | K99: =(D99-B99)/B99 -> -0.78350152 | L99: =(E99-B99) -> -195028 | M99: =(E99/B99) -> 0.016966239 | N99: =(E99-B99)/B99 -> -0.98303376
A100: ИТОГО ДОЛГОСРОЧНЫЕ ОБЯЗАТЕЛЬСТВА | B100: 1013282 | C100: 956598 | D100: 1002911 | E100: 1096908 | F100: =(C100-B100) -> -56684 | G100: =(C100/B100) -> 0.94405901 | H100: =(C100-B100)/B100 -> -0.055940992 | I100: =(D100-B100) -> -10371 | J100: =(D100/B100) -> 0.98976494 | K100: =(D100-B100)/B100 -> -0.010235058 | L100: =(E100-B100) -> 83626 | M100: =(E100/B100) -> 1.0825298 | N100: =(E100-B100)/B100 -> 0.082529839
A101: КРАТКОСРОЧНЫЕ ОБЯЗАТЕЛЬСТВА
A102: Краткосрочные займы | B102: 112998 | C102: 65342 | D102: 122395 | E102: 160242 | F102: =(C102-B102) -> -47656 | G102: =(C102/B102) -> 0.57825802 | H102: =(C102-B102)/B102 -> -0.42174198 | I102: =(D102-B102) -> 9397 | J102: =(D102/B102) -> 1.0831608 | K102: =(D102-B102)/B102 -> 0.083160764 | L102: =(E102-B102) -> 47244 | M102: =(E102/B102) -> 1.4180959 | N102: =(E102-B102)/B102 -> 0.4180959
A103: Текущий налог на прибыль | B103: 2812 | C103: 1480 | D103: 3731 | E103: 2958 | F103: =(C103-B103) -> -1332 | G103: =(C103/B103) -> 0.52631579 | H103: =(C103-B103)/B103 -> -0.47368421 | I103: =(D103-B103) -> 919 | J103: =(D103/B103) -> 1.3268137 | K103: =(D103-B103)/B103 -> 0.32681366 | L103: =(E103-B103) -> 146 | M103: =(E103/B103) -> 1.0519203 | N103: =(E103-B103)/B103 -> 0.051920341
A104: Краткосрочная часть долгосрочных займов | B104: 87764 | C104: 106782 | D104: 56238 | E104: 29682 | F104: =(C104-B104) -> 19018 | G104: =(C104/B104) -> 1.2166948 | H104: =(C104-B104)/B104 -> 0.21669477 | I104: =(D104-B104) -> -31526 | J104: =(D104/B104) -> 0.64078666 | K104: =(D104-B104)/B104 -> -0.35921334 | L104: =(E104-B104) -> -58082 | M104: =(E104/B104) -> 0.33820245 | N104: =(E104-B104)/B104 -> -0.66179755
...

Sheet Графики
A7: Выручка
B8: Аэрофлот | C8: Ютэер | D8: TurkishAirlines
A9: 2020 г. | B9: 302182 | C9: 56037 | D9: 498316
A10: 2021 г. | B10: 491733 | C10: 76752 | D10: 790764
A11: 2023 г. | B11: 612194 | C11: 99655 | D11: 1905722
A12: 2024 г. | B12: 856785 | C12: 113344 | D12: 2312238
O25: операционные расходы
A26: Темп роста выручки
B27: Аэрофлот | C27: Ютэер | D27: TurkishAirlines
A28: 2021 г. | B28: =(B10-B9)*100/B9 -> 62.727429 | C28: =(C10-C9)*100/C9 -> 36.966647 | D28: =(D10-D9)*100/D9 -> 58.687259
A29: 2023 г. | B29: =(B11-B10)*100/B10 -> 24.497237 | C29: =(C11-C10)*100/C10 -> 29.840265 | D29: =(D11-D10)*100/D10 -> 140.99757
A30: 2024 г. | B30: =(B12-B11)*100/B11 -> 39.953185 | C30: =(C12-C11)*100/C11 -> 13.736391 | D30: =(D12-D11)*100/D11 -> 21.331338
N42: Заёмные средства = Краткосрочные кредиты и займы + Долгосрочные кредиты и займы | V42: Собственный капитал
A43: Активы | O43: Аэрофлот | Q43: Ютэер | S43: TurkishAirlines | W43: Аэрофлот | X43: Ютэер | Y43: TurkishAirlines
B44: Аэрофлот | C44: Ютэер | D44: TurkishAirlines | N44: 2020 г. | O44: ='Аэрофлот'!B39+'Аэрофлот'!B44 -> 88635 | Q44: ='Ютэер'!B59+'Ютэер'!B47 -> 61496 | S44: =TurkishAirlines!B60+TurkishAirlines!B72+TurkishAirlines!B73 -> 399156 | V44: 2020 г. | W44: -115346 | X44: -4925 | Y44: 398342
A45: 2020 г. | B45: 1016204 | C45: 86106 | D45: 1889220 | N45: 2021 г. | O45: ='Аэрофлот'!C39+'Аэрофлот'!C44 -> 132268 | Q45: ='Ютэер'!C59+'Ютэер'!C47 -> 25152 | S45: =TurkishAirlines!C60+TurkishAirlines!C72+TurkishAirlines!C73 -> 344766 | V45: 2021 г. | W45: -146438 | X45: 10801 | Y45: 505938
A46: 2021 г. | B46: 1109450 | C46: 95458 | D46: 1963738 | N46: 2023 г. | O46: ='Аэрофлот'!D39+'Аэрофлот'!D44 -> 104368 | Q46: ='Ютэер'!D59+'Ютэер'!D47 -> 30744 | S46: =TurkishAirlines!D60+TurkishAirlines!D72+TurkishAirlines!D73 -> 221585 | V46: 2023 г. | W46: -98754 | X46: 23067 | Y46: 1416233
A47: 2023 г. | B47: 1114014 | C47: 123163 | D47: 3246061 | N47: 2024 г. | O47: ='Аэрофлот'!E39+'Аэрофлот'!E44 -> 60468 | Q47: ='Ютэер'!E59+'Ютэер'!E47 -> 31109 | S47: =TurkishAirlines!E60+TurkishAirlines!E72+TurkishAirlines!E73 -> 193290 | V47: 2024 г. | W47: -72497 | X47: 14445 | Y47: 1970028
A48: 2024 г. | B48: 1156896 | C48: 130350 | D48: 4046748
A52: Темп роста активов
B53: Аэрофлот | C53: Ютэер | D53: TurkishAirlines
A54: 2021 г. | B54: =(B46-B45)*100/B45 -> 9.1759135 | C54: =(C46-C45)*100/C45 -> 10.861032 | D54: =(D46-D45)*100/D45 -> 3.9443792
A55: 2023 г. | B55: =(B47-B46)*100/B46 -> 0.41137501 | C55: =(C47-C46)*100/C46 -> 29.023235 | D55: =(D47-D46)*100/D46 -> 65.300106
A56: 2024 г. | B56: =(B48-B47)*100/B47 -> 3.8493233 | C56: =(C48-C47)*100/C47 -> 5.8353564 | D56: =(D48-D47)*100/D47 -> 24.666419
A65: Чистая прибыль
B66: Аэрофлот | C66: Ютэер | D66: TurkishAirlines
A67: 2020 г. | B67: -123208 | C67: 3130 | D67: -61864
A68: 2021 г. | B68: -34460 | C68: 26825 | D68: 70966
A69: 2023 г. | B69: -14021 | C69: 2786 | D69: 547911
A70: 2024 г. | B70: 55020 | C70: -7015 | D70: 349350
A72: Темп роста чистой прибыли
B73: Аэрофлот | C73: Ютэер | D73: TurkishAirlines
A74: 2021 г. | B74: =(B68-B67)*100/abs(B67) -> 72.031037 | C74: =(C68-C67)*100/C67 -> 757.02875 | D74: =(D68-D67)*100/abs(D67) -> 214.71292
A75: 2023 г. | B75: =(B69-B68)*100/abs(B68) -> 59.312246 | C75: =(C69-C68)*100/C68 -> -89.614166 | D75: =(D69-D68)*100/D68 -> 672.07536
A76: 2024 г. | B76: =(B70-B69)*100/abs(B69) -> 492.41138 | C76: =(C70-C69)*100/C69 -> -351.79469 | D76: =(D70-D69)*100/D69 -> -36.239645
A92: Графики из Горизонтального анализа
A95: Денежные средства и их эквиваленты
A96: Год | B96: Аэрофлот | C96: Ютэир | D96: TurkishAirlines | E96: Общеотраслевые показатели
A97: 2020г | B97: 88944 | C97: 12679 | D97: 134014 | E97: 145171
A98: 2021г | B98: 74180 | C98: 7569 | D98: 198098 | E98: 161576
A99: 2023г | B99: 83117 | C99: 5537 | D99: 62153 | E99: -
A100: 2024г | B100: 67814 | C100: 5337 | D100: 277542 | E100: -
A102: Изменения в структуре капитала Аэрофлота
B103: Уставный капитал | C103: Добавочный капитал | D103: Капитал, приходящийся на акционеров компании | E103: Держатели неконтролирующих долей участия
A104: 2020г | B104: 2693 | C104: 78701 | D104: -107776 | E104: -7570
A105: 2021г | B105: 2693 | C105: 78701 | D105: -138501 | E105: -7937
A106: 2023г | B106: 4224 | C106: 144402 | D106: -85543 | E106: -13211
A107: 2024г | B107: 4224 | C107: 143482 | D107: -55712 | E107: -16785
A109: Изменения в обязательствах Аэрофлота
A110: год | B110: Краткосрочные кредиты и займы и краткосрочная часть долгосрочных кредитов и займов | C110: Обязательства по текущему налогу на прибыль | D110: Долгосрочные кредиты и займы | E110: Прочие долгосрочные обязательства | F110: Итого краткосрочные обязательства | G110: Итого долгосрочные обязательства
A111: 2020г | B111: 34924 | C111: 4 | D111: 53711 | E111: 20666 | F111: 281285 | G111: 850265
A112: 2021г | B112: 17500 | C112: 141 | D112: 114768 | E112: 15552 | F112: 272588 | G112: 983300
A113: 2023г | B113: 44178 | C113: 905 | D113: 60190 | E113: 9913 | F113: 339604 | G113: 873164
A114: 2024г | B114: 19746 | C114: 754 | D114: 40722 | E114: 4982 | F114: 409065 | G114: 820328
